{
"meta":{"test_sets":[],"test_metrics":[],"learn_metrics":[{"best_value":"Min","name":"RMSE"}],"launch_mode":"Train","parameters":"","iteration_count":1000,"learn_sets":["learn"],"name":"experiment"},
"iterations":[
{"learn":[14.59871775],"iteration":0,"passed_time":0.06093569932,"remaining_time":60.87476362},
{"learn":[14.22518863],"iteration":1,"passed_time":0.06138464868,"remaining_time":30.63093969},
{"learn":[13.8866124],"iteration":2,"passed_time":0.06189980506,"remaining_time":20.57136855},
{"learn":[13.52356875],"iteration":3,"passed_time":0.0623279215,"remaining_time":15.51965245},
{"learn":[13.18870211],"iteration":4,"passed_time":0.06269920575,"remaining_time":12.47714194},
{"learn":[12.9124226],"iteration":5,"passed_time":0.06317873784,"remaining_time":10.4666109},
{"learn":[12.60003351],"iteration":6,"passed_time":0.06355789693,"remaining_time":9.016141665},
{"learn":[12.32990573],"iteration":7,"passed_time":0.06394122261,"remaining_time":7.928711603},
{"learn":[12.0660619],"iteration":8,"passed_time":0.06434254792,"remaining_time":7.084829443},
{"learn":[11.77309809],"iteration":9,"passed_time":0.06473033184,"remaining_time":6.408302852},
{"learn":[11.49227636],"iteration":10,"passed_time":0.06510044945,"remaining_time":5.853122228},
{"learn":[11.26264833],"iteration":11,"passed_time":0.06552835757,"remaining_time":5.395168106},
{"learn":[11.04260393],"iteration":12,"passed_time":0.06586993408,"remaining_time":5.001048072},
{"learn":[10.79916926],"iteration":13,"passed_time":0.06623871837,"remaining_time":4.665098308},
{"learn":[10.5541002],"iteration":14,"passed_time":0.06663891871,"remaining_time":4.375955662},
{"learn":[10.31918115],"iteration":15,"passed_time":0.06709545126,"remaining_time":4.126370252},
{"learn":[10.10004441],"iteration":16,"passed_time":0.06749236,"remaining_time":3.902646463},
{"learn":[9.894556723],"iteration":17,"passed_time":0.06786839415,"remaining_time":3.702597948},
{"learn":[9.690174082],"iteration":18,"passed_time":0.06827621934,"remaining_time":3.525209009},
{"learn":[9.506034866],"iteration":19,"passed_time":0.0686550451,"remaining_time":3.36409721},
{"learn":[9.338524633],"iteration":20,"passed_time":0.06903445419,"remaining_time":3.218320507},
{"learn":[9.170203312],"iteration":21,"passed_time":0.06939232204,"remaining_time":3.084804134},
{"learn":[9.010299969],"iteration":22,"passed_time":0.06977927264,"remaining_time":2.964102147},
{"learn":[8.843866678],"iteration":23,"passed_time":0.07087508408,"remaining_time":2.882253419},
{"learn":[8.690548059],"iteration":24,"passed_time":0.07127328446,"remaining_time":2.779658094},
{"learn":[8.555307687],"iteration":25,"passed_time":0.07162598575,"remaining_time":2.68321962},
{"learn":[8.413851302],"iteration":26,"passed_time":0.07197956202,"remaining_time":2.593930142},
{"learn":[8.29256019],"iteration":27,"passed_time":0.07234084647,"remaining_time":2.511260813},
{"learn":[8.162193833],"iteration":28,"passed_time":0.07271342236,"remaining_time":2.434645969},
{"learn":[8.040736294],"iteration":29,"passed_time":0.07310045629,"remaining_time":2.36358142},
{"learn":[7.921220278],"iteration":30,"passed_time":0.07354823901,"remaining_time":2.2989756},
{"learn":[7.809589039],"iteration":31,"passed_time":0.07394410611,"remaining_time":2.23680921},
{"learn":[7.699675801],"iteration":32,"passed_time":0.07434247315,"remaining_time":2.178459743},
{"learn":[7.60645267],"iteration":33,"passed_time":0.07474367347,"remaining_time":2.123599664},
{"learn":[7.498880302],"iteration":34,"passed_time":0.07521149745,"remaining_time":2.07368843},
{"learn":[7.401158744],"iteration":35,"passed_time":0.07563853059,"remaining_time":2.025431764},
{"learn":[7.306431077],"iteration":36,"passed_time":0.07613731229,"remaining_time":1.981627885},
{"learn":[7.223863468],"iteration":37,"passed_time":0.07656026217,"remaining_time":1.938183479},
{"learn":[7.143477682],"iteration":38,"passed_time":0.07696729571,"remaining_time":1.896553107},
{"learn":[7.062817131],"iteration":39,"passed_time":0.07735745458,"remaining_time":1.85657891},
{"learn":[6.990793435],"iteration":40,"passed_time":0.07779098759,"remaining_time":1.819550173},
{"learn":[6.931862224],"iteration":41,"passed_time":0.07824652015,"remaining_time":1.784765864},
{"learn":[6.858296558],"iteration":42,"passed_time":0.07870217772,"remaining_time":1.751581025},
{"learn":[6.786268161],"iteration":43,"passed_time":0.07912662757,"remaining_time":1.719205817},
{"learn":[6.717118549],"iteration":44,"passed_time":0.07959615986,"remaining_time":1.689207393},
{"learn":[6.652948106],"iteration":45,"passed_time":0.08010723298,"remaining_time":1.661354354},
{"learn":[6.589686076],"iteration":46,"passed_time":0.08059188997,"remaining_time":1.634129173},
{"learn":[6.531283097],"iteration":47,"passed_time":0.08106267223,"remaining_time":1.607742999},
{"learn":[6.471368031],"iteration":48,"passed_time":0.08146470586,"remaining_time":1.581080312},
{"learn":[6.416481395],"iteration":49,"passed_time":0.08190644704,"remaining_time":1.556222494},
{"learn":[6.369870822],"iteration":50,"passed_time":0.08234139668,"remaining_time":1.532195793},
{"learn":[6.325678067],"iteration":51,"passed_time":0.08281892881,"remaining_time":1.509852779},
{"learn":[6.275766122],"iteration":52,"passed_time":0.08323842043,"remaining_time":1.487297814},
{"learn":[6.224773967],"iteration":53,"passed_time":0.08363328754,"remaining_time":1.465131297},
{"learn":[6.182249254],"iteration":54,"passed_time":0.08407444539,"remaining_time":1.444551834},
{"learn":[6.139904173],"iteration":55,"passed_time":0.08447322909,"remaining_time":1.42397729},
{"learn":[6.100525536],"iteration":56,"passed_time":0.08509634164,"remaining_time":1.407821933},
{"learn":[6.062568564],"iteration":57,"passed_time":0.085495792,"remaining_time":1.388569587},
{"learn":[6.030559288],"iteration":58,"passed_time":0.08588999246,"remaining_time":1.369872592},
{"learn":[5.997931376],"iteration":59,"passed_time":0.08631440064,"remaining_time":1.352258943},
{"learn":[5.964103835],"iteration":60,"passed_time":0.08672830904,"remaining_time":1.335047249},
{"learn":[5.933729724],"iteration":61,"passed_time":0.08716821692,"remaining_time":1.318770766},
{"learn":[5.901932711],"iteration":62,"passed_time":0.08758241698,"remaining_time":1.302614678},
{"learn":[5.873727795],"iteration":63,"passed_time":0.08818307164,"remaining_time":1.289677423},
{"learn":[5.846485734],"iteration":64,"passed_time":0.08861381304,"remaining_time":1.274675618},
{"learn":[5.820630862],"iteration":65,"passed_time":0.08899380545,"remaining_time":1.259397186},
{"learn":[5.793646238],"iteration":66,"passed_time":0.08942108858,"remaining_time":1.245222025},
{"learn":[5.765388646],"iteration":67,"passed_time":0.08984083019,"remaining_time":1.231347849},
{"learn":[5.747073912],"iteration":68,"passed_time":0.09029757107,"remaining_time":1.218362879},
{"learn":[5.722315217],"iteration":69,"passed_time":0.0906815634,"remaining_time":1.204769342},
{"learn":[5.699970599],"iteration":70,"passed_time":0.09105988917,"remaining_time":1.191473761},
{"learn":[5.682732647],"iteration":71,"passed_time":0.09154117122,"remaining_time":1.179863985},
{"learn":[5.663525791],"iteration":72,"passed_time":0.09194045491,"remaining_time":1.167517832},
{"learn":[5.642381613],"iteration":73,"passed_time":0.0923748629,"remaining_time":1.155934095},
{"learn":[5.621404779],"iteration":74,"passed_time":0.09286635308,"remaining_time":1.145351688},
{"learn":[5.602460129],"iteration":75,"passed_time":0.09334409354,"remaining_time":1.134867664},
{"learn":[5.587337574],"iteration":76,"passed_time":0.09391920705,"remaining_time":1.125810755},
{"learn":[5.572393026],"iteration":77,"passed_time":0.09437223967,"remaining_time":1.115528269},
{"learn":[5.558425806],"iteration":78,"passed_time":0.09482693892,"remaining_time":1.10551406},
{"learn":[5.541518902],"iteration":79,"passed_time":0.09525838863,"remaining_time":1.095471469},
{"learn":[5.526157283],"iteration":80,"passed_time":0.09569800485,"remaining_time":1.085758845},
{"learn":[5.511746977],"iteration":81,"passed_time":0.09615945396,"remaining_time":1.076516814},
{"learn":[5.504975022],"iteration":82,"passed_time":0.09632103407,"remaining_time":1.064173352},
{"learn":[5.493980522],"iteration":83,"passed_time":0.09672798427,"remaining_time":1.054795638},
{"learn":[5.480745463],"iteration":84,"passed_time":0.09712785128,"remaining_time":1.045552752},
{"learn":[5.464052013],"iteration":85,"passed_time":0.09748021924,"remaining_time":1.036010702},
{"learn":[5.449143727],"iteration":86,"passed_time":0.09788083624,"remaining_time":1.027186247},
{"learn":[5.438255432],"iteration":87,"passed_time":0.09825124551,"remaining_time":1.018240181},
{"learn":[5.425927931],"iteration":88,"passed_time":0.09869244503,"remaining_time":1.010211432},
{"learn":[5.412331217],"iteration":89,"passed_time":0.09907935396,"remaining_time":1.001802357},
{"learn":[5.400691499],"iteration":90,"passed_time":0.0994713878,"remaining_time":0.9936207858},
{"learn":[5.391618744],"iteration":91,"passed_time":0.09995258652,"remaining_time":0.9864885713},
{"learn":[5.380766572],"iteration":92,"passed_time":0.1003601617,"remaining_time":0.978781362},
{"learn":[5.372207183],"iteration":93,"passed_time":0.1008093611,"remaining_time":0.9716306503},
{"learn":[5.362918837],"iteration":94,"passed_time":0.1013383922,"remaining_time":0.9653815254},
{"learn":[5.348292324],"iteration":95,"passed_time":0.1017736335,"remaining_time":0.9583683819},
{"learn":[5.339772295],"iteration":96,"passed_time":0.1021910001,"remaining_time":0.9513244652},
{"learn":[5.331515983],"iteration":97,"passed_time":0.1025820757,"remaining_time":0.9441737984},
{"learn":[5.323861644],"iteration":98,"passed_time":0.1031276898,"remaining_time":0.9385661461},
{"learn":[5.313277281],"iteration":99,"passed_time":0.1035536396,"remaining_time":0.9319827562},
{"learn":[5.30685627],"iteration":100,"passed_time":0.103948965,"remaining_time":0.9252487084},
{"learn":[5.29652059],"iteration":101,"passed_time":0.1044349553,"remaining_time":0.9194371555},
{"learn":[5.288350766],"iteration":102,"passed_time":0.1048920295,"remaining_time":0.913477189},
{"learn":[5.27993346],"iteration":103,"passed_time":0.1053544369,"remaining_time":0.9076689951},
{"learn":[5.271789139],"iteration":104,"passed_time":0.105751929,"remaining_time":0.9014092995},
{"learn":[5.262684686],"iteration":105,"passed_time":0.106184712,"remaining_time":0.8955578542},
{"learn":[5.251619772],"iteration":106,"passed_time":0.1065802458,"remaining_time":0.8894968176},
{"learn":[5.241012171],"iteration":107,"passed_time":0.1070773608,"remaining_time":0.884379684},
{"learn":[5.232684032],"iteration":108,"passed_time":0.1074792278,"remaining_time":0.8785687338},
{"learn":[5.224267141],"iteration":109,"passed_time":0.107988051,"remaining_time":0.8737215035},
{"learn":[5.216324968],"iteration":110,"passed_time":0.1083859597,"remaining_time":0.8680641277},
{"learn":[5.211102527],"iteration":111,"passed_time":0.1087990348,"remaining_time":0.8626209187},
{"learn":[5.206364257],"iteration":112,"passed_time":0.1092251513,"remaining_time":0.8573691078},
{"learn":[5.196937641],"iteration":113,"passed_time":0.1096953085,"remaining_time":0.8525442401},
{"learn":[5.190746047],"iteration":114,"passed_time":0.1101614659,"remaining_time":0.8477643246},
{"learn":[5.181885213],"iteration":115,"passed_time":0.1105422083,"remaining_time":0.8424078632},
{"learn":[5.178293568],"iteration":116,"passed_time":0.1108968262,"remaining_time":0.8369392953},
{"learn":[5.170991438],"iteration":117,"passed_time":0.1115464799,"remaining_time":0.8337626718},
{"learn":[5.166257212],"iteration":118,"passed_time":0.112025012,"remaining_time":0.8293616435},
{"learn":[5.161421246],"iteration":119,"passed_time":0.1124608366,"remaining_time":0.824712802},
{"learn":[5.158223542],"iteration":120,"passed_time":0.1128649119,"remaining_time":0.819902955},
{"learn":[5.15470988],"iteration":121,"passed_time":0.1132159882,"remaining_time":0.8147839152},
{"learn":[5.146388143],"iteration":122,"passed_time":0.1136275633,"remaining_time":0.8101737645},
{"learn":[5.139529364],"iteration":123,"passed_time":0.1140658879,"remaining_time":0.8058203048},
{"learn":[5.134276023],"iteration":124,"passed_time":0.1144972126,"remaining_time":0.8014804883},
{"learn":[5.128536065],"iteration":125,"passed_time":0.1149571618,"remaining_time":0.7974012649},
{"learn":[5.123300353],"iteration":126,"passed_time":0.1158878932,"remaining_time":0.7966152026},
{"learn":[5.116200518],"iteration":127,"passed_time":0.1162983016,"remaining_time":0.7922821799},
{"learn":[5.108728704],"iteration":128,"passed_time":0.1167692506,"remaining_time":0.7884187383},
{"learn":[5.104075866],"iteration":129,"passed_time":0.1172705322,"remaining_time":0.7848104848},
{"learn":[5.100317606],"iteration":130,"passed_time":0.1177548975,"remaining_time":0.7811374501},
{"learn":[5.095814182],"iteration":131,"passed_time":0.1181735558,"remaining_time":0.7770806551},
{"learn":[5.092146915],"iteration":132,"passed_time":0.1185831727,"remaining_time":0.7730196293},
{"learn":[5.085258329],"iteration":133,"passed_time":0.1190219972,"remaining_time":0.7692018627},
{"learn":[5.079219421],"iteration":134,"passed_time":0.119466405,"remaining_time":0.7654699284},
{"learn":[5.076476829],"iteration":135,"passed_time":0.1198723136,"remaining_time":0.7615417568},
{"learn":[5.072133867],"iteration":136,"passed_time":0.1202723056,"remaining_time":0.7576277351},
{"learn":[5.067031564],"iteration":137,"passed_time":0.1207598375,"remaining_time":0.7543114488},
{"learn":[5.061358312],"iteration":138,"passed_time":0.1211797458,"remaining_time":0.7506169865},
{"learn":[5.056759124],"iteration":139,"passed_time":0.1215975291,"remaining_time":0.7469562502},
{"learn":[5.050254],"iteration":140,"passed_time":0.122018479,"remaining_time":0.7433608049},
{"learn":[5.048376474],"iteration":141,"passed_time":0.1222676824,"remaining_time":0.7387723344},
{"learn":[5.042603751],"iteration":142,"passed_time":0.1227080903,"remaining_time":0.735390443},
{"learn":[5.037477349],"iteration":143,"passed_time":0.1231727476,"remaining_time":0.7321935554},
{"learn":[5.03230489],"iteration":144,"passed_time":0.123602489,"remaining_time":0.7288284699},
{"learn":[5.025976187],"iteration":145,"passed_time":0.1241456449,"remaining_time":0.7261669912},
{"learn":[5.01952451],"iteration":146,"passed_time":0.124538387,"remaining_time":0.7226615247},
{"learn":[5.017569424],"iteration":147,"passed_time":0.1250050027,"remaining_time":0.7196233939},
{"learn":[5.008962367],"iteration":148,"passed_time":0.1254697017,"remaining_time":0.7166088335},
{"learn":[5.003880266],"iteration":149,"passed_time":0.1260163992,"remaining_time":0.7140929286},
{"learn":[4.996387564],"iteration":150,"passed_time":0.1264157662,"remaining_time":0.7107747383},
{"learn":[4.993361683],"iteration":151,"passed_time":0.126824008,"remaining_time":0.7075444658},
{"learn":[4.99005752],"iteration":152,"passed_time":0.1272651242,"remaining_time":0.7045330733},
{"learn":[4.986908764],"iteration":153,"passed_time":0.127642825,"remaining_time":0.701206688},
{"learn":[4.985207175],"iteration":154,"passed_time":0.1281006909,"remaining_time":0.6983553792},
{"learn":[4.979003494],"iteration":155,"passed_time":0.128545307,"remaining_time":0.695463071},
{"learn":[4.973142217],"iteration":156,"passed_time":0.1289487572,"remaining_time":0.6923809067},
{"learn":[4.967056696],"iteration":157,"passed_time":0.1293729571,"remaining_time":0.6894432271},
{"learn":[4.961460696],"iteration":158,"passed_time":0.1298289063,"remaining_time":0.6867050957},
{"learn":[4.954240363],"iteration":159,"passed_time":0.130212982,"remaining_time":0.6836181554},
{"learn":[4.952320707],"iteration":160,"passed_time":0.1304510606,"remaining_time":0.679803974},
{"learn":[4.948337777],"iteration":161,"passed_time":0.1308443027,"remaining_time":0.6768365782},
{"learn":[4.943228639],"iteration":162,"passed_time":0.1313752088,"remaining_time":0.6746076671},
{"learn":[4.938545759],"iteration":163,"passed_time":0.1318200332,"remaining_time":0.6719606571},
{"learn":[4.935330572],"iteration":164,"passed_time":0.1322936071,"remaining_time":0.6694858298},
{"learn":[4.932051543],"iteration":165,"passed_time":0.1327477647,"remaining_time":0.6669375647},
{"learn":[4.928964153],"iteration":166,"passed_time":0.1331717562,"remaining_time":0.6642639097},
{"learn":[4.922860227],"iteration":167,"passed_time":0.1336160807,"remaining_time":0.6617177328},
{"learn":[4.917668772],"iteration":168,"passed_time":0.134031989,"remaining_time":0.6590567034},
{"learn":[4.910365386],"iteration":169,"passed_time":0.134468397,"remaining_time":0.6565221735},
{"learn":[4.906457206],"iteration":170,"passed_time":0.1348811804,"remaining_time":0.6538976523},
{"learn":[4.901996508],"iteration":171,"passed_time":0.1353217133,"remaining_time":0.6514324336},
{"learn":[4.896816173],"iteration":172,"passed_time":0.1357515797,"remaining_time":0.6489396323},
{"learn":[4.891123132],"iteration":173,"passed_time":0.1361368636,"remaining_time":0.6462589044},
{"learn":[4.887630202],"iteration":174,"passed_time":0.1365228559,"remaining_time":0.6436077494},
{"learn":[4.885259712],"iteration":175,"passed_time":0.1370013047,"remaining_time":0.6414151993},
{"learn":[4.880659728],"iteration":176,"passed_time":0.1374101715,"remaining_time":0.6389184812},
{"learn":[4.877299723],"iteration":177,"passed_time":0.1378275799,"remaining_time":0.6364846666},
{"learn":[4.874038772],"iteration":178,"passed_time":0.1382958205,"remaining_time":0.6343065287},
{"learn":[4.86943698],"iteration":179,"passed_time":0.138703979,"remaining_time":0.6318736822},
{"learn":[4.861268711],"iteration":180,"passed_time":0.1390841381,"remaining_time":0.6293365144},
{"learn":[4.858673056],"iteration":181,"passed_time":0.1396590849,"remaining_time":0.6276985246},
{"learn":[4.854036207],"iteration":182,"passed_time":0.1400863681,"remaining_time":0.625412911},
{"learn":[4.85130244],"iteration":183,"passed_time":0.1405777749,"remaining_time":0.6234318714},
{"learn":[4.847510084],"iteration":184,"passed_time":0.1410445573,"remaining_time":0.621358455},
{"learn":[4.845691673],"iteration":185,"passed_time":0.1414663822,"remaining_time":0.619105565},
{"learn":[4.842058646],"iteration":186,"passed_time":0.1418904987,"remaining_time":0.6168822216},
{"learn":[4.838623675],"iteration":187,"passed_time":0.1424099467,"remaining_time":0.6150897696},
{"learn":[4.834602161],"iteration":188,"passed_time":0.1428000222,"remaining_time":0.6127556508},
{"learn":[4.830858976],"iteration":189,"passed_time":0.1432186805,"remaining_time":0.6105638484},
{"learn":[4.827590511],"iteration":190,"passed_time":0.1437023792,"remaining_time":0.6086660982},
{"learn":[4.822246226],"iteration":191,"passed_time":0.1441709115,"remaining_time":0.6067192525},
{"learn":[4.816686395],"iteration":192,"passed_time":0.1446324856,"remaining_time":0.6047586314},
{"learn":[4.814797121],"iteration":193,"passed_time":0.1450204362,"remaining_time":0.6025075853},
{"learn":[4.811639392],"iteration":194,"passed_time":0.1454608857,"remaining_time":0.6004923743},
{"learn":[4.804813432],"iteration":195,"passed_time":0.1459268347,"remaining_time":0.5985978323},
{"learn":[4.80251613],"iteration":196,"passed_time":0.1463477013,"remaining_time":0.5965340313},
{"learn":[4.800087884],"iteration":197,"passed_time":0.1467240271,"remaining_time":0.5943064129},
{"learn":[4.794773135],"iteration":198,"passed_time":0.1471061028,"remaining_time":0.5921205446},
{"learn":[4.791664833],"iteration":199,"passed_time":0.1475280944,"remaining_time":0.5901123776},
{"learn":[4.785989873],"iteration":200,"passed_time":0.14791717,"remaining_time":0.5879891483},
{"learn":[4.782387142],"iteration":201,"passed_time":0.1483160787,"remaining_time":0.5859219345},
{"learn":[4.778623704],"iteration":202,"passed_time":0.1487264038,"remaining_time":0.5839159794},
{"learn":[4.775772178],"iteration":203,"passed_time":0.1491199793,"remaining_time":0.5818603113},
{"learn":[4.77023101],"iteration":204,"passed_time":0.1495283878,"remaining_time":0.5798783819},
{"learn":[4.764496689],"iteration":205,"passed_time":0.1499722122,"remaining_time":0.5780482355},
{"learn":[4.763138716],"iteration":206,"passed_time":0.1503707459,"remaining_time":0.5760579784},
{"learn":[4.758053283],"iteration":207,"passed_time":0.15075128,"remaining_time":0.5740144893},
{"learn":[4.755063788],"iteration":208,"passed_time":0.1511221476,"remaining_time":0.571950329},
{"learn":[4.752465267],"iteration":209,"passed_time":0.1515160981,"remaining_time":0.5699891308},
{"learn":[4.748067377],"iteration":210,"passed_time":0.151936923,"remaining_time":0.5681432808},
{"learn":[4.744163298],"iteration":211,"passed_time":0.1523617478,"remaining_time":0.566325742},
{"learn":[4.736670896],"iteration":212,"passed_time":0.152769073,"remaining_time":0.564456622},
{"learn":[4.73349255],"iteration":213,"passed_time":0.1531644401,"remaining_time":0.5625572428},
{"learn":[4.731864595],"iteration":214,"passed_time":0.1535645988,"remaining_time":0.5606893491},
{"learn":[4.728398311],"iteration":215,"passed_time":0.1540013401,"remaining_time":0.558967827},
{"learn":[4.723865975],"iteration":216,"passed_time":0.1543946656,"remaining_time":0.5571014891},
{"learn":[4.723483365],"iteration":217,"passed_time":0.1547761163,"remaining_time":0.5552060685},
{"learn":[4.72095416],"iteration":218,"passed_time":0.1551663585,"remaining_time":0.5533558264},
{"learn":[4.716173382],"iteration":219,"passed_time":0.155557684,"remaining_time":0.5515226978},
{"learn":[4.710563974],"iteration":220,"passed_time":0.1559983835,"remaining_time":0.549876655},
{"learn":[4.707160263],"iteration":221,"passed_time":0.1564262083,"remaining_time":0.5481963516},
{"learn":[4.70408351],"iteration":222,"passed_time":0.1569297816,"remaining_time":0.5467912121},
{"learn":[4.702501831],"iteration":223,"passed_time":0.1573693145,"remaining_time":0.545172268},
{"learn":[4.700269738],"iteration":224,"passed_time":0.1577513902,"remaining_time":0.5433658995},
{"learn":[4.695346302],"iteration":225,"passed_time":0.1581596737,"remaining_time":0.5416618913},
{"learn":[4.689769299],"iteration":226,"passed_time":0.1585719571,"remaining_time":0.53998292},
{"learn":[4.687919514],"iteration":227,"passed_time":0.1591231544,"remaining_time":0.5387854176},
{"learn":[4.682982074],"iteration":228,"passed_time":0.1595510625,"remaining_time":0.5371784682},
{"learn":[4.679578702],"iteration":229,"passed_time":0.1600066784,"remaining_time":0.5356745322},
{"learn":[4.675751423],"iteration":230,"passed_time":0.1605351679,"remaining_time":0.5344222689},
{"learn":[4.672710726],"iteration":231,"passed_time":0.1610774904,"remaining_time":0.5332220371},
{"learn":[4.6690533],"iteration":232,"passed_time":0.1615593974,"remaining_time":0.5318285744},
{"learn":[4.667595702],"iteration":233,"passed_time":0.1620154716,"remaining_time":0.5303583388},
{"learn":[4.664241291],"iteration":234,"passed_time":0.1624085055,"remaining_time":0.5286915178},
{"learn":[4.662246999],"iteration":235,"passed_time":0.1628822043,"remaining_time":0.5272966276},
{"learn":[4.658668443],"iteration":236,"passed_time":0.1633746945,"remaining_time":0.525970008},
{"learn":[4.658017572],"iteration":237,"passed_time":0.1637566452,"remaining_time":0.5242964859},
{"learn":[4.657656705],"iteration":238,"passed_time":0.1642552602,"remaining_time":0.5230052428},
{"learn":[4.653242871],"iteration":239,"passed_time":0.1646456691,"remaining_time":0.5213779522},
{"learn":[4.6507302],"iteration":240,"passed_time":0.165065744,"remaining_time":0.5198543557},
{"learn":[4.647671336],"iteration":241,"passed_time":0.1654779858,"remaining_time":0.518315344},
{"learn":[4.645506007],"iteration":242,"passed_time":0.1658552699,"remaining_time":0.5166767051},
{"learn":[4.641297906],"iteration":243,"passed_time":0.1663274272,"remaining_time":0.5153423563},
{"learn":[4.63798107],"iteration":244,"passed_time":0.166750877,"remaining_time":0.5138649476},
{"learn":[4.635062318],"iteration":245,"passed_time":0.1671397859,"remaining_time":0.5122902382},
{"learn":[4.631606017],"iteration":246,"passed_time":0.1675490278,"remaining_time":0.510787117},
{"learn":[4.630215494],"iteration":247,"passed_time":0.1679505614,"remaining_time":0.5092694443},
{"learn":[4.62729814],"iteration":248,"passed_time":0.1683995524,"remaining_time":0.507903871},
{"learn":[4.624691756],"iteration":249,"passed_time":0.1688163774,"remaining_time":0.5064491323},
{"learn":[4.621840053],"iteration":250,"passed_time":0.1692254526,"remaining_time":0.5049795379},
{"learn":[4.619602091],"iteration":251,"passed_time":0.1696156948,"remaining_time":0.5034624592},
{"learn":[4.613584029],"iteration":252,"passed_time":0.1700101869,"remaining_time":0.5019668365},
{"learn":[4.6119388],"iteration":253,"passed_time":0.1704535531,"remaining_time":0.5006234275},
{"learn":[4.60870702],"iteration":254,"passed_time":0.1708407953,"remaining_time":0.499123108},
{"learn":[4.604771557],"iteration":255,"passed_time":0.1712598286,"remaining_time":0.497723877},
{"learn":[4.604231277],"iteration":256,"passed_time":0.1716764036,"remaining_time":0.496325167},
{"learn":[4.600750354],"iteration":257,"passed_time":0.172060396,"remaining_time":0.4948403636},
{"learn":[4.596488253],"iteration":258,"passed_time":0.1724576797,"remaining_time":0.4934020875},
{"learn":[4.59470784],"iteration":259,"passed_time":0.1728582134,"remaining_time":0.4919810688},
{"learn":[4.588818005],"iteration":260,"passed_time":0.1733229958,"remaining_time":0.4907497849},
{"learn":[4.585054174],"iteration":261,"passed_time":0.1737811116,"remaining_time":0.4895055739},
{"learn":[4.581471435],"iteration":262,"passed_time":0.1742265194,"remaining_time":0.4882317292},
{"learn":[4.577555199],"iteration":263,"passed_time":0.1747456757,"remaining_time":0.4871697625},
{"learn":[4.57457145],"iteration":264,"passed_time":0.1751847502,"remaining_time":0.4858897789},
{"learn":[4.573029224],"iteration":265,"passed_time":0.1756316163,"remaining_time":0.4846376179},
{"learn":[4.571326203],"iteration":266,"passed_time":0.1761046068,"remaining_time":0.4834632091},
{"learn":[4.571019224],"iteration":267,"passed_time":0.1765565562,"remaining_time":0.4822365638},
{"learn":[4.565766631],"iteration":268,"passed_time":0.1771043785,"remaining_time":0.4812762108},
{"learn":[4.563383471],"iteration":269,"passed_time":0.1774976624,"remaining_time":0.4799010871},
{"learn":[4.558165805],"iteration":270,"passed_time":0.177880988,"remaining_time":0.4785064217},
{"learn":[4.55629209],"iteration":271,"passed_time":0.178300063,"remaining_time":0.4772148745},
{"learn":[4.549383848],"iteration":272,"passed_time":0.1788127611,"remaining_time":0.4761790377},
{"learn":[4.546227503],"iteration":273,"passed_time":0.1792175863,"remaining_time":0.4748611959},
{"learn":[4.540620977],"iteration":274,"passed_time":0.1796075369,"remaining_time":0.473510779},
{"learn":[4.532898237],"iteration":275,"passed_time":0.1800161954,"remaining_time":0.4722163966},
{"learn":[4.529757367],"iteration":276,"passed_time":0.1804668947,"remaining_time":0.4710381403},
{"learn":[4.52579294],"iteration":277,"passed_time":0.1808519287,"remaining_time":0.4696945773},
{"learn":[4.521572155],"iteration":278,"passed_time":0.1812730453,"remaining_time":0.4684511313},
{"learn":[4.518818099],"iteration":279,"passed_time":0.1816877453,"remaining_time":0.4671970594},
{"learn":[4.514012334],"iteration":280,"passed_time":0.1821066953,"remaining_time":0.465959836},
{"learn":[4.508331416],"iteration":281,"passed_time":0.1825601029,"remaining_time":0.4648161485},
{"learn":[4.506038537],"iteration":282,"passed_time":0.1829843444,"remaining_time":0.463603445},
{"learn":[4.505805643],"iteration":283,"passed_time":0.183357462,"remaining_time":0.4622674041},
{"learn":[4.501550352],"iteration":284,"passed_time":0.1837822868,"remaining_time":0.4610678423},
{"learn":[4.494692643],"iteration":285,"passed_time":0.1841949869,"remaining_time":0.4598434288},
{"learn":[4.489330245],"iteration":286,"passed_time":0.1847286846,"remaining_time":0.4589252686},
{"learn":[4.484826955],"iteration":287,"passed_time":0.1851439263,"remaining_time":0.4577169288},
{"learn":[4.478285428],"iteration":288,"passed_time":0.1855921256,"remaining_time":0.4565951603},
{"learn":[4.475311671],"iteration":289,"passed_time":0.1860198671,"remaining_time":0.4554279505},
{"learn":[4.471581298],"iteration":290,"passed_time":0.1864034844,"remaining_time":0.4541583177},
{"learn":[4.469164956],"iteration":291,"passed_time":0.1868128096,"remaining_time":0.4529570863},
{"learn":[4.462068024],"iteration":292,"passed_time":0.1872395927,"remaining_time":0.4518033859},
{"learn":[4.458540976],"iteration":293,"passed_time":0.1877201665,"remaining_time":0.4507838011},
{"learn":[4.455757458],"iteration":294,"passed_time":0.1881022422,"remaining_time":0.449532477},
{"learn":[4.453027414],"iteration":295,"passed_time":0.1885326086,"remaining_time":0.4484018798},
{"learn":[4.450659338],"iteration":296,"passed_time":0.1889741831,"remaining_time":0.4473025276},
{"learn":[4.444696901],"iteration":297,"passed_time":0.189393258,"remaining_time":0.4461545877},
{"learn":[4.442052813],"iteration":298,"passed_time":0.189895123,"remaining_time":0.4452056229},
{"learn":[4.440036756],"iteration":299,"passed_time":0.1903096564,"remaining_time":0.4440558649},
{"learn":[4.435017051],"iteration":300,"passed_time":0.1907129817,"remaining_time":0.4428849641},
{"learn":[4.429962125],"iteration":301,"passed_time":0.191195597,"remaining_time":0.4419024064},
{"learn":[4.427666256],"iteration":302,"passed_time":0.191579131,"remaining_time":0.4406952288},
{"learn":[4.425030004],"iteration":303,"passed_time":0.1919887062,"remaining_time":0.4395530905},
{"learn":[4.422588771],"iteration":304,"passed_time":0.1924529886,"remaining_time":0.4385404166},
{"learn":[4.418936667],"iteration":305,"passed_time":0.1928901882,"remaining_time":0.4374699039},
{"learn":[4.416887976],"iteration":306,"passed_time":0.1933781368,"remaining_time":0.4365180742},
{"learn":[4.413773354],"iteration":307,"passed_time":0.1938010866,"remaining_time":0.4354232207},
{"learn":[4.411129391],"iteration":308,"passed_time":0.1942205783,"remaining_time":0.4343249825},
{"learn":[4.40850819],"iteration":309,"passed_time":0.1947469011,"remaining_time":0.4334689089},
{"learn":[4.404880292],"iteration":310,"passed_time":0.1951579345,"remaining_time":0.4323595399},
{"learn":[4.404593827],"iteration":311,"passed_time":0.1955639264,"remaining_time":0.4312435301},
{"learn":[4.402139942],"iteration":312,"passed_time":0.1959413356,"remaining_time":0.4300693212},
{"learn":[4.400284725],"iteration":313,"passed_time":0.1963752019,"remaining_time":0.4290235302},
{"learn":[4.395805521],"iteration":314,"passed_time":0.1968281095,"remaining_time":0.4280230318},
{"learn":[4.392838833],"iteration":315,"passed_time":0.1972515177,"remaining_time":0.4269621459},
{"learn":[4.389213061],"iteration":316,"passed_time":0.1977586743,"remaining_time":0.426085724},
{"learn":[4.3861981],"iteration":317,"passed_time":0.1982424146,"remaining_time":0.4251614049},
{"learn":[4.385054234],"iteration":318,"passed_time":0.1986337401,"remaining_time":0.4240425612},
{"learn":[4.379364607],"iteration":319,"passed_time":0.1991491881,"remaining_time":0.4231920248},
{"learn":[4.378387619],"iteration":320,"passed_time":0.1995375554,"remaining_time":0.4220747667},
{"learn":[4.375816727],"iteration":321,"passed_time":0.1999657135,"remaining_time":0.4210458191},
{"learn":[4.374600202],"iteration":322,"passed_time":0.2003897884,"remaining_time":0.4200120332},
{"learn":[4.37098897],"iteration":323,"passed_time":0.2008579873,"remaining_time":0.4190740723},
{"learn":[4.367418484],"iteration":324,"passed_time":0.2013083117,"remaining_time":0.4181018781},
{"learn":[4.363584638],"iteration":325,"passed_time":0.201709012,"remaining_time":0.4170302886},
{"learn":[4.360770706],"iteration":326,"passed_time":0.2021207121,"remaining_time":0.4159854411},
{"learn":[4.358675808],"iteration":327,"passed_time":0.2025364538,"remaining_time":0.4149527346},
{"learn":[4.354228195],"iteration":328,"passed_time":0.2029179878,"remaining_time":0.4138540117},
{"learn":[4.353773425],"iteration":329,"passed_time":0.2032887304,"remaining_time":0.4127377254},
{"learn":[4.351648009],"iteration":330,"passed_time":0.2036955556,"remaining_time":0.4116988723},
{"learn":[4.348209927],"iteration":331,"passed_time":0.2041945457,"remaining_time":0.4108492666},
{"learn":[4.345852733],"iteration":332,"passed_time":0.2046076208,"remaining_time":0.4098296788},
{"learn":[4.34237339],"iteration":333,"passed_time":0.2050243624,"remaining_time":0.4088210341},
{"learn":[4.340814362],"iteration":334,"passed_time":0.2054970197,"remaining_time":0.4079269196},
{"learn":[4.339707068],"iteration":335,"passed_time":0.2060228008,"remaining_time":0.4071402969},
{"learn":[4.335430786],"iteration":336,"passed_time":0.2064388342,"remaining_time":0.4061393088},
{"learn":[4.33521887],"iteration":337,"passed_time":0.2067849939,"remaining_time":0.4050049289},
{"learn":[4.328507238],"iteration":338,"passed_time":0.207248818,"remaining_time":0.4041046274},
{"learn":[4.326140732],"iteration":339,"passed_time":0.2077061005,"remaining_time":0.4031941951},
{"learn":[4.323785636],"iteration":340,"passed_time":0.2081530916,"remaining_time":0.4022665319},
{"learn":[4.320632534],"iteration":341,"passed_time":0.2085412088,"remaining_time":0.4012284077},
{"learn":[4.31973724],"iteration":342,"passed_time":0.208951034,"remaining_time":0.400235654},
{"learn":[4.318000924],"iteration":343,"passed_time":0.2093558592,"remaining_time":0.3992367548},
{"learn":[4.312713628],"iteration":344,"passed_time":0.209818725,"remaining_time":0.3983514924},
{"learn":[4.308220789],"iteration":345,"passed_time":0.2103172567,"remaining_time":0.3975360864},
{"learn":[4.305890947],"iteration":346,"passed_time":0.2107798308,"remaining_time":0.3966548401},
{"learn":[4.305137856],"iteration":347,"passed_time":0.2111736979,"remaining_time":0.3956472731},
{"learn":[4.304787172],"iteration":348,"passed_time":0.2115551486,"remaining_time":0.3946200623},
{"learn":[4.30350134],"iteration":349,"passed_time":0.211922433,"remaining_time":0.3935702326},
{"learn":[4.30293809],"iteration":350,"passed_time":0.2123329664,"remaining_time":0.3926042599},
{"learn":[4.299548459],"iteration":351,"passed_time":0.2127675411,"remaining_time":0.3916857006},
{"learn":[4.294768408],"iteration":352,"passed_time":0.2131649915,"remaining_time":0.3907018399},
{"learn":[4.294581479],"iteration":353,"passed_time":0.2135675251,"remaining_time":0.3897305684},
{"learn":[4.292551604],"iteration":354,"passed_time":0.2139791002,"remaining_time":0.3887789285},
{"learn":[4.288628894],"iteration":355,"passed_time":0.2145010898,"remaining_time":0.3880300613},
{"learn":[4.287802767],"iteration":356,"passed_time":0.2149168731,"remaining_time":0.3870911749},
{"learn":[4.284566905],"iteration":357,"passed_time":0.2153566977,"remaining_time":0.3861983238},
{"learn":[4.27890232],"iteration":358,"passed_time":0.2157527314,"remaining_time":0.3852298074},
{"learn":[4.276938023],"iteration":359,"passed_time":0.2161598483,"remaining_time":0.3842841748},
{"learn":[4.273425094],"iteration":360,"passed_time":0.2166354638,"remaining_time":0.3834627739},
{"learn":[4.269726505],"iteration":361,"passed_time":0.2170792049,"remaining_time":0.382587107},
{"learn":[4.265565857],"iteration":362,"passed_time":0.2174686972,"remaining_time":0.3816186228},
{"learn":[4.262117173],"iteration":363,"passed_time":0.2179242714,"remaining_time":0.3807687819},
{"learn":[4.259185148],"iteration":364,"passed_time":0.2183300133,"remaining_time":0.3798344067},
{"learn":[4.257668507],"iteration":365,"passed_time":0.2187665462,"remaining_time":0.3789562577},
{"learn":[4.253432436],"iteration":366,"passed_time":0.2192242871,"remaining_time":0.3781170946},
{"learn":[4.250216667],"iteration":367,"passed_time":0.2196226125,"remaining_time":0.3771779649},
{"learn":[4.24514828],"iteration":368,"passed_time":0.220031146,"remaining_time":0.3762592225},
{"learn":[4.244015772],"iteration":369,"passed_time":0.2204243881,"remaining_time":0.3753172014},
{"learn":[4.240329192],"iteration":370,"passed_time":0.2208439214,"remaining_time":0.3744227131},
{"learn":[4.236718014],"iteration":371,"passed_time":0.2212401218,"remaining_time":0.3734913884},
{"learn":[4.233495944],"iteration":372,"passed_time":0.2216468637,"remaining_time":0.3725806529},
{"learn":[4.230357491],"iteration":373,"passed_time":0.2220756885,"remaining_time":0.3717095748},
{"learn":[4.227381215],"iteration":374,"passed_time":0.2224793887,"remaining_time":0.3707989812},
{"learn":[4.226169067],"iteration":375,"passed_time":0.2228862139,"remaining_time":0.3698962699},
{"learn":[4.225963861],"iteration":376,"passed_time":0.2234039536,"remaining_time":0.3691794777},
{"learn":[4.224346548],"iteration":377,"passed_time":0.223783571,"remaining_time":0.3682364581},
{"learn":[4.222595381],"iteration":378,"passed_time":0.224202021,"remaining_time":0.3673600396},
{"learn":[4.219700938],"iteration":379,"passed_time":0.2245864716,"remaining_time":0.366430559},
{"learn":[4.216356207],"iteration":380,"passed_time":0.2250517957,"remaining_time":0.3656353321},
{"learn":[4.214326494],"iteration":381,"passed_time":0.2254404962,"remaining_time":0.3647178709},
{"learn":[4.212901398],"iteration":382,"passed_time":0.2258253635,"remaining_time":0.3637969956},
{"learn":[4.211331091],"iteration":383,"passed_time":0.2262228139,"remaining_time":0.3628990974},
{"learn":[4.208624791],"iteration":384,"passed_time":0.226637264,"remaining_time":0.3620309542},
{"learn":[4.204659106],"iteration":385,"passed_time":0.2270428809,"remaining_time":0.3611511111},
{"learn":[4.202968852],"iteration":386,"passed_time":0.2274576643,"remaining_time":0.3602882382},
{"learn":[4.197261935],"iteration":387,"passed_time":0.22792178,"remaining_time":0.359505488},
{"learn":[4.196934403],"iteration":388,"passed_time":0.2283261469,"remaining_time":0.358630529},
{"learn":[4.192479929],"iteration":389,"passed_time":0.2287577633,"remaining_time":0.3578006041},
{"learn":[4.190243116],"iteration":390,"passed_time":0.2291466722,"remaining_time":0.3569061979},
{"learn":[4.185852431],"iteration":391,"passed_time":0.2295551224,"remaining_time":0.3560446796},
{"learn":[4.180967944],"iteration":392,"passed_time":0.2299852804,"remaining_time":0.3552189955},
{"learn":[4.178283162],"iteration":393,"passed_time":0.2303646479,"remaining_time":0.3543171995},
{"learn":[4.176341157],"iteration":394,"passed_time":0.2307866394,"remaining_time":0.3534833338},
{"learn":[4.176041504],"iteration":395,"passed_time":0.2312447969,"remaining_time":0.3527067105},
{"learn":[4.175564513],"iteration":396,"passed_time":0.2316512888,"remaining_time":0.351853217},
{"learn":[4.170830274],"iteration":397,"passed_time":0.2320235314,"remaining_time":0.3509501656},
{"learn":[4.167804808],"iteration":398,"passed_time":0.2323982739,"remaining_time":0.3500535404},
{"learn":[4.165860548],"iteration":399,"passed_time":0.2327776413,"remaining_time":0.349166462},
{"learn":[4.160950571],"iteration":400,"passed_time":0.2331860082,"remaining_time":0.3483252341},
{"learn":[4.158544115],"iteration":401,"passed_time":0.2336402074,"remaining_time":0.3475543384},
{"learn":[4.154448767],"iteration":402,"passed_time":0.2341061981,"remaining_time":0.3468024821},
{"learn":[4.15197457],"iteration":403,"passed_time":0.2345974383,"remaining_time":0.3460892902},
{"learn":[4.149562679],"iteration":404,"passed_time":0.2349741808,"remaining_time":0.3452089816},
{"learn":[4.149327961],"iteration":405,"passed_time":0.2354021306,"remaining_time":0.3444060728},
{"learn":[4.147444889],"iteration":406,"passed_time":0.2358912041,"remaining_time":0.343694064},
{"learn":[4.147254809],"iteration":407,"passed_time":0.2363156123,"remaining_time":0.3428893198},
{"learn":[4.144589165],"iteration":408,"passed_time":0.2366900632,"remaining_time":0.3420142477},
{"learn":[4.141691034],"iteration":409,"passed_time":0.2370689306,"remaining_time":0.3411479733},
{"learn":[4.138893468],"iteration":410,"passed_time":0.2375190049,"remaining_time":0.3403861166},
{"learn":[4.136964597],"iteration":411,"passed_time":0.2379489963,"remaining_time":0.3395971113},
{"learn":[4.133773523],"iteration":412,"passed_time":0.2384121121,"remaining_time":0.3388569245},
{"learn":[4.131363444],"iteration":413,"passed_time":0.2388012293,"remaining_time":0.3380133343},
{"learn":[4.130228592],"iteration":414,"passed_time":0.2392466371,"remaining_time":0.3372512836},
{"learn":[4.12884186],"iteration":415,"passed_time":0.2396436292,"remaining_time":0.3364227871},
{"learn":[4.12413494],"iteration":416,"passed_time":0.2400638708,"remaining_time":0.3356288649},
{"learn":[4.119422508],"iteration":417,"passed_time":0.240483529,"remaining_time":0.3348359184},
{"learn":[4.117038244],"iteration":418,"passed_time":0.2409024373,"remaining_time":0.3340437138},
{"learn":[4.116067631],"iteration":419,"passed_time":0.2412796798,"remaining_time":0.3331957483},
{"learn":[4.110343455],"iteration":420,"passed_time":0.2416511724,"remaining_time":0.3323421112},
{"learn":[4.105604544],"iteration":421,"passed_time":0.2420706223,"remaining_time":0.3315564448},
{"learn":[4.103390131],"iteration":422,"passed_time":0.2425926536,"remaining_time":0.3309124376},
{"learn":[4.096724402],"iteration":423,"passed_time":0.2429960622,"remaining_time":0.3301078581},
{"learn":[4.093431279],"iteration":424,"passed_time":0.2433797629,"remaining_time":0.3292785027},
{"learn":[4.091412744],"iteration":425,"passed_time":0.2438102543,"remaining_time":0.3285142862},
{"learn":[4.091192901],"iteration":426,"passed_time":0.2442035381,"remaining_time":0.3277017033},
{"learn":[4.088994581],"iteration":427,"passed_time":0.2445783639,"remaining_time":0.3268664116},
{"learn":[4.087845355],"iteration":428,"passed_time":0.2449765226,"remaining_time":0.3260643226},
{"learn":[4.083650279],"iteration":429,"passed_time":0.2453803062,"remaining_time":0.3252715687},
{"learn":[4.079840652],"iteration":430,"passed_time":0.2457987979,"remaining_time":0.3245000371},
{"learn":[4.075707828],"iteration":431,"passed_time":0.2462087063,"remaining_time":0.3237188546},
{"learn":[4.071345409],"iteration":432,"passed_time":0.2466370728,"remaining_time":0.3229635572},
{"learn":[4.067460475],"iteration":433,"passed_time":0.2470209818,"remaining_time":0.3221517873},
{"learn":[4.064914749],"iteration":434,"passed_time":0.2474840142,"remaining_time":0.3214447541},
{"learn":[4.063823175],"iteration":435,"passed_time":0.2479042141,"remaining_time":0.320683433},
{"learn":[4.058898471],"iteration":436,"passed_time":0.248362205,"remaining_time":0.3199723602},
{"learn":[4.054120355],"iteration":437,"passed_time":0.2488069878,"remaining_time":0.3192454957},
{"learn":[4.052715901],"iteration":438,"passed_time":0.2492623953,"remaining_time":0.3185334938},
{"learn":[4.052114167],"iteration":439,"passed_time":0.2496293463,"remaining_time":0.3177100771},
{"learn":[4.051377267],"iteration":440,"passed_time":0.2500398798,"remaining_time":0.3169439746},
{"learn":[4.049275336],"iteration":441,"passed_time":0.2504660796,"remaining_time":0.3161992589},
{"learn":[4.047099198],"iteration":442,"passed_time":0.2509402785,"remaining_time":0.3155163321},
{"learn":[4.044348685],"iteration":443,"passed_time":0.2513322706,"remaining_time":0.314731402},
{"learn":[4.042822379],"iteration":444,"passed_time":0.2517970947,"remaining_time":0.3140390732},
{"learn":[4.041258611],"iteration":445,"passed_time":0.2523982077,"remaining_time":0.3135170562},
{"learn":[4.040044254],"iteration":446,"passed_time":0.2527995747,"remaining_time":0.3127475722},
{"learn":[4.036860137],"iteration":447,"passed_time":0.2532075665,"remaining_time":0.3119878945},
{"learn":[4.036372284],"iteration":448,"passed_time":0.2536127668,"remaining_time":0.3112263574},
{"learn":[4.03368231],"iteration":449,"passed_time":0.2540075505,"remaining_time":0.3104536729},
{"learn":[4.032439519],"iteration":450,"passed_time":0.2544026676,"remaining_time":0.3096830699},
{"learn":[4.032008634],"iteration":451,"passed_time":0.2548058679,"remaining_time":0.3089239284},
{"learn":[4.030034932],"iteration":452,"passed_time":0.2552191513,"remaining_time":0.3081785337},
{"learn":[4.028173412],"iteration":453,"passed_time":0.2555999354,"remaining_time":0.307395517},
{"learn":[4.023806097],"iteration":454,"passed_time":0.2560112605,"remaining_time":0.3066508505},
{"learn":[4.020239186],"iteration":455,"passed_time":0.2564615848,"remaining_time":0.3059541714},
{"learn":[4.017384838],"iteration":456,"passed_time":0.2568594936,"remaining_time":0.305196291},
{"learn":[4.016468229],"iteration":457,"passed_time":0.2573909829,"remaining_time":0.3045980628},
{"learn":[4.014530169],"iteration":458,"passed_time":0.2578365157,"remaining_time":0.3038988126},
{"learn":[4.012884822],"iteration":459,"passed_time":0.2582538407,"remaining_time":0.3031675521},
{"learn":[4.008924707],"iteration":460,"passed_time":0.2586512494,"remaining_time":0.3024143676},
{"learn":[4.008286778],"iteration":461,"passed_time":0.259108657,"remaining_time":0.3017325919},
{"learn":[4.006444202],"iteration":462,"passed_time":0.2595374401,"remaining_time":0.301018586},
{"learn":[4.003284363],"iteration":463,"passed_time":0.2599399737,"remaining_time":0.3002754868},
{"learn":[3.999811484],"iteration":464,"passed_time":0.2604191724,"remaining_time":0.2996220586},
{"learn":[3.997483319],"iteration":465,"passed_time":0.2608484555,"remaining_time":0.2989121787},
{"learn":[3.99708333],"iteration":466,"passed_time":0.26129128,"remaining_time":0.2982189556},
{"learn":[3.995860263],"iteration":467,"passed_time":0.2617253547,"remaining_time":0.2975168562},
{"learn":[3.994131111],"iteration":468,"passed_time":0.2621458879,"remaining_time":0.2968005682},
{"learn":[3.993125499],"iteration":469,"passed_time":0.2625446716,"remaining_time":0.2960610127},
{"learn":[3.992954084],"iteration":470,"passed_time":0.2629423304,"remaining_time":0.2953216407},
{"learn":[3.990635743],"iteration":471,"passed_time":0.2633513222,"remaining_time":0.2945963943},
{"learn":[3.986678254],"iteration":472,"passed_time":0.2637885635,"remaining_time":0.2939039597},
{"learn":[3.986393291],"iteration":473,"passed_time":0.2641720141,"remaining_time":0.2931529102},
{"learn":[3.986152671],"iteration":474,"passed_time":0.2645564648,"remaining_time":0.2924045137},
{"learn":[3.985596662],"iteration":475,"passed_time":0.2649378738,"remaining_time":0.2916542981},
{"learn":[3.983853457],"iteration":476,"passed_time":0.2653538655,"remaining_time":0.2909435465},
{"learn":[3.983263928],"iteration":477,"passed_time":0.2657498576,"remaining_time":0.2902121876},
{"learn":[3.980067202],"iteration":478,"passed_time":0.2661401832,"remaining_time":0.2894760656},
{"learn":[3.978115407],"iteration":479,"passed_time":0.2665644247,"remaining_time":0.2887781267},
{"learn":[3.972661644],"iteration":480,"passed_time":0.2669566252,"remaining_time":0.2880467536},
{"learn":[3.969938254],"iteration":481,"passed_time":0.2673677836,"remaining_time":0.2873371617},
{"learn":[3.968211434],"iteration":482,"passed_time":0.2678689403,"remaining_time":0.286725139},
{"learn":[3.966113368],"iteration":483,"passed_time":0.2682639324,"remaining_time":0.2860003907},
{"learn":[3.962246044],"iteration":484,"passed_time":0.2686835907,"remaining_time":0.2853031942},
{"learn":[3.961319703],"iteration":485,"passed_time":0.2690784161,"remaining_time":0.2845808763},
{"learn":[3.96078191],"iteration":486,"passed_time":0.2694582835,"remaining_time":0.2838441467},
{"learn":[3.958913633],"iteration":487,"passed_time":0.2698357343,"remaining_time":0.2831063442},
{"learn":[3.957428286],"iteration":488,"passed_time":0.2702481844,"remaining_time":0.2824065894},
{"learn":[3.952641965],"iteration":489,"passed_time":0.2706263852,"remaining_time":0.2816723601},
{"learn":[3.951486786],"iteration":490,"passed_time":0.2710100859,"remaining_time":0.2809452825},
{"learn":[3.94938344],"iteration":491,"passed_time":0.2714307858,"remaining_time":0.2802578032},
{"learn":[3.947297924],"iteration":492,"passed_time":0.2718707353,"remaining_time":0.2795912025},
{"learn":[3.946284886],"iteration":493,"passed_time":0.2722790605,"remaining_time":0.2788931268},
{"learn":[3.943288204],"iteration":494,"passed_time":0.2726709693,"remaining_time":0.2781794738},
{"learn":[3.943076488],"iteration":495,"passed_time":0.27305717,"remaining_time":0.2774613179},
{"learn":[3.942347078],"iteration":496,"passed_time":0.2734897863,"remaining_time":0.2767914739},
{"learn":[3.940251541],"iteration":497,"passed_time":0.2739158611,"remaining_time":0.2761159885},
{"learn":[3.939011019],"iteration":498,"passed_time":0.2743255613,"remaining_time":0.2754250625},
{"learn":[3.938760512],"iteration":499,"passed_time":0.2747148452,"remaining_time":0.2747148452},
{"learn":[3.934522727],"iteration":500,"passed_time":0.2751271286,"remaining_time":0.2740288167},
{"learn":[3.930091193],"iteration":501,"passed_time":0.2755142459,"remaining_time":0.2733189132},
{"learn":[3.927671752],"iteration":502,"passed_time":0.2759927363,"remaining_time":0.2727005764},
{"learn":[3.927280041],"iteration":503,"passed_time":0.2764050614,"remaining_time":0.2720176795},
{"learn":[3.925987561],"iteration":504,"passed_time":0.2767712624,"remaining_time":0.2712906434},
{"learn":[3.921645957],"iteration":505,"passed_time":0.2772395447,"remaining_time":0.2706646939},
{"learn":[3.920333743],"iteration":506,"passed_time":0.2776815776,"remaining_time":0.2700138417},
{"learn":[3.918659461],"iteration":507,"passed_time":0.2781183605,"remaining_time":0.2693587271},
{"learn":[3.916124385],"iteration":508,"passed_time":0.2785213941,"remaining_time":0.2686719146},
{"learn":[3.913849268],"iteration":509,"passed_time":0.2789046365,"remaining_time":0.2679671998},
{"learn":[3.912826119],"iteration":510,"passed_time":0.2792947537,"remaining_time":0.267270322},
{"learn":[3.910034145],"iteration":511,"passed_time":0.2797322866,"remaining_time":0.2666198357},
{"learn":[3.90792379],"iteration":512,"passed_time":0.2801863192,"remaining_time":0.265985843},
{"learn":[3.907823851],"iteration":513,"passed_time":0.2805947277,"remaining_time":0.2653094118},
{"learn":[3.904527401],"iteration":514,"passed_time":0.2810149277,"remaining_time":0.264645126},
{"learn":[3.903378283],"iteration":515,"passed_time":0.2814202112,"remaining_time":0.263967795},
{"learn":[3.902170135],"iteration":516,"passed_time":0.2818197449,"remaining_time":0.2632861447},
{"learn":[3.899435429],"iteration":517,"passed_time":0.2822617361,"remaining_time":0.2626450903},
{"learn":[3.897497505],"iteration":518,"passed_time":0.2827224769,"remaining_time":0.2620221799},
{"learn":[3.896426119],"iteration":519,"passed_time":0.283231425,"remaining_time":0.2614443923},
{"learn":[3.896044669],"iteration":520,"passed_time":0.2836288338,"remaining_time":0.2607643213},
{"learn":[3.892795942],"iteration":521,"passed_time":0.2840609918,"remaining_time":0.2601171534},
{"learn":[3.892413888],"iteration":522,"passed_time":0.2844749002,"remaining_time":0.2594541633},
{"learn":[3.891738985],"iteration":523,"passed_time":0.2848696423,"remaining_time":0.2587747132},
{"learn":[3.88822057],"iteration":524,"passed_time":0.2852905506,"remaining_time":0.2581200219},
{"learn":[3.883837053],"iteration":525,"passed_time":0.2856825427,"remaining_time":0.2574401621},
{"learn":[3.881769742],"iteration":526,"passed_time":0.2860697017,"remaining_time":0.2567570567},
{"learn":[3.880356898],"iteration":527,"passed_time":0.2864710687,"remaining_time":0.2560877735},
{"learn":[3.879250273],"iteration":528,"passed_time":0.2869075183,"remaining_time":0.2554507393},
{"learn":[3.877174493],"iteration":529,"passed_time":0.2872907606,"remaining_time":0.2547672783},
{"learn":[3.875854201],"iteration":530,"passed_time":0.28765492,"remaining_time":0.2540680932},
{"learn":[3.873189396],"iteration":531,"passed_time":0.288090453,"remaining_time":0.2534329549},
{"learn":[3.871583368],"iteration":532,"passed_time":0.2884879034,"remaining_time":0.2527651986},
{"learn":[3.869622679],"iteration":533,"passed_time":0.2888816455,"remaining_time":0.2520952187},
{"learn":[3.866860164],"iteration":534,"passed_time":0.2893120119,"remaining_time":0.2514581038},
{"learn":[3.864498444],"iteration":535,"passed_time":0.2898271683,"remaining_time":0.2508951606},
{"learn":[3.861416322],"iteration":536,"passed_time":0.2902597846,"remaining_time":0.2502612296},
{"learn":[3.860265769],"iteration":537,"passed_time":0.2906688598,"remaining_time":0.2496078313},
{"learn":[3.859328725],"iteration":538,"passed_time":0.2910775183,"remaining_time":0.2489549832},
{"learn":[3.858521278],"iteration":539,"passed_time":0.2914765103,"remaining_time":0.2482948051},
{"learn":[3.85599111],"iteration":540,"passed_time":0.2919414594,"remaining_time":0.2476915524},
{"learn":[3.852379816],"iteration":541,"passed_time":0.2923641176,"remaining_time":0.2470530735},
{"learn":[3.851327537],"iteration":542,"passed_time":0.2927551514,"remaining_time":0.2463887739},
{"learn":[3.847854898],"iteration":543,"passed_time":0.2931679349,"remaining_time":0.2457437101},
{"learn":[3.847083414],"iteration":544,"passed_time":0.2935654269,"remaining_time":0.2450867326},
{"learn":[3.845397429],"iteration":545,"passed_time":0.2939513359,"remaining_time":0.2444210742},
{"learn":[3.841933528],"iteration":546,"passed_time":0.2943554945,"remaining_time":0.2437715521},
{"learn":[3.840996474],"iteration":547,"passed_time":0.2947513199,"remaining_time":0.2431160522},
{"learn":[3.838355966],"iteration":548,"passed_time":0.295196186,"remaining_time":0.2425017849},
{"learn":[3.83342799],"iteration":549,"passed_time":0.2955759701,"remaining_time":0.2418348846},
{"learn":[3.828161535],"iteration":550,"passed_time":0.2959722955,"remaining_time":0.2411825058},
{"learn":[3.823502399],"iteration":551,"passed_time":0.2963849539,"remaining_time":0.2405443104},
{"learn":[3.820068862],"iteration":552,"passed_time":0.296880319,"remaining_time":0.2399737841},
{"learn":[3.817951642],"iteration":553,"passed_time":0.2973576012,"remaining_time":0.2393889713},
{"learn":[3.815785958],"iteration":554,"passed_time":0.297766093,"remaining_time":0.2387493899},
{"learn":[3.81503012],"iteration":555,"passed_time":0.2981527519,"remaining_time":0.2380932048},
{"learn":[3.813529315],"iteration":556,"passed_time":0.2986007013,"remaining_time":0.2374867337},
{"learn":[3.808881326],"iteration":557,"passed_time":0.29900061,"remaining_time":0.2368427771},
{"learn":[3.808740434],"iteration":558,"passed_time":0.2993948105,"remaining_time":0.2361951904},
{"learn":[3.80714352],"iteration":559,"passed_time":0.2998369683,"remaining_time":0.2355861894},
{"learn":[3.80573346],"iteration":560,"passed_time":0.3002708346,"remaining_time":0.2349712948},
{"learn":[3.803370052],"iteration":561,"passed_time":0.3006579936,"remaining_time":0.2343206427},
{"learn":[3.803215211],"iteration":562,"passed_time":0.3010913599,"remaining_time":0.2337067927},
{"learn":[3.801309667],"iteration":563,"passed_time":0.3015203513,"remaining_time":0.2330902007},
{"learn":[3.800003847],"iteration":564,"passed_time":0.3021287142,"remaining_time":0.2326123729},
{"learn":[3.798026138],"iteration":565,"passed_time":0.3025497474,"remaining_time":0.2319904424},
{"learn":[3.794745847],"iteration":566,"passed_time":0.3030105299,"remaining_time":0.2313995757},
{"learn":[3.794312041],"iteration":567,"passed_time":0.30342298,"remaining_time":0.2307724073},
{"learn":[3.792205926],"iteration":568,"passed_time":0.3038144305,"remaining_time":0.2301300871},
{"learn":[3.788991061],"iteration":569,"passed_time":0.3042269223,"remaining_time":0.2295045203},
{"learn":[3.787391572],"iteration":570,"passed_time":0.30459204,"remaining_time":0.2288441071},
{"learn":[3.7826445],"iteration":571,"passed_time":0.3050126982,"remaining_time":0.2282262847},
{"learn":[3.781700331],"iteration":572,"passed_time":0.305410732,"remaining_time":0.2275922907},
{"learn":[3.780045374],"iteration":573,"passed_time":0.3058805559,"remaining_time":0.2270123986},
{"learn":[3.775462644],"iteration":574,"passed_time":0.3063124639,"remaining_time":0.2264048646},
{"learn":[3.773711943],"iteration":575,"passed_time":0.30675883,"remaining_time":0.2258085832},
{"learn":[3.772415806],"iteration":576,"passed_time":0.3071741967,"remaining_time":0.2251900957},
{"learn":[3.770170875],"iteration":577,"passed_time":0.30759423,"remaining_time":0.2245757181},
{"learn":[3.765166479],"iteration":578,"passed_time":0.3079835972,"remaining_time":0.223939714},
{"learn":[3.763976102],"iteration":579,"passed_time":0.3084055055,"remaining_time":0.2233281246},
{"learn":[3.760761708],"iteration":580,"passed_time":0.308827247,"remaining_time":0.222717068},
{"learn":[3.758155662],"iteration":581,"passed_time":0.3093514032,"remaining_time":0.2221802174},
{"learn":[3.756844548],"iteration":582,"passed_time":0.3097524785,"remaining_time":0.2215553749},
{"learn":[3.753098923],"iteration":583,"passed_time":0.3101498873,"remaining_time":0.2209286868},
{"learn":[3.751618946],"iteration":584,"passed_time":0.310528463,"remaining_time":0.2202894225},
{"learn":[3.751398464],"iteration":585,"passed_time":0.3109246635,"remaining_time":0.2196634994},
{"learn":[3.749920103],"iteration":586,"passed_time":0.3113160723,"remaining_time":0.2190349878},
{"learn":[3.748237465],"iteration":587,"passed_time":0.3117191893,"remaining_time":0.2184154864},
{"learn":[3.746021536],"iteration":588,"passed_time":0.3121368059,"remaining_time":0.2178068374},
{"learn":[3.74417648],"iteration":589,"passed_time":0.3125753388,"remaining_time":0.217213371},
{"learn":[3.738788389],"iteration":590,"passed_time":0.3129886222,"remaining_time":0.2166029551},
{"learn":[3.736021611],"iteration":591,"passed_time":0.3134220302,"remaining_time":0.2160070749},
{"learn":[3.734546151],"iteration":592,"passed_time":0.3138325637,"remaining_time":0.2153960429},
{"learn":[3.733527479],"iteration":593,"passed_time":0.3142279725,"remaining_time":0.2147753482},
{"learn":[3.733026392],"iteration":594,"passed_time":0.3146782551,"remaining_time":0.2141927619},
{"learn":[3.730314752],"iteration":595,"passed_time":0.3151123715,"remaining_time":0.2135996612},
{"learn":[3.727342596],"iteration":596,"passed_time":0.3155317798,"remaining_time":0.2129971646},
{"learn":[3.725459604],"iteration":597,"passed_time":0.3159265635,"remaining_time":0.2123787267},
{"learn":[3.723158842],"iteration":598,"passed_time":0.3163090559,"remaining_time":0.211752807},
{"learn":[3.722362756],"iteration":599,"passed_time":0.3167632552,"remaining_time":0.2111755034},
{"learn":[3.721443615],"iteration":600,"passed_time":0.3171619555,"remaining_time":0.2105617641},
{"learn":[3.720743486],"iteration":601,"passed_time":0.3175362397,"remaining_time":0.209932597},
{"learn":[3.720215334],"iteration":602,"passed_time":0.3179051073,"remaining_time":0.2093007091},
{"learn":[3.719436563],"iteration":603,"passed_time":0.3183267239,"remaining_time":0.2087042759},
{"learn":[3.715046574],"iteration":604,"passed_time":0.3187393823,"remaining_time":0.2081025719},
{"learn":[3.71443396],"iteration":605,"passed_time":0.3191294579,"remaining_time":0.2074868093},
{"learn":[3.712938941],"iteration":606,"passed_time":0.3195178668,"remaining_time":0.2068707111},
{"learn":[3.712814764],"iteration":607,"passed_time":0.3198984842,"remaining_time":0.2062503385},
{"learn":[3.71235348],"iteration":608,"passed_time":0.320309976,"remaining_time":0.2056505757},
{"learn":[3.711223749],"iteration":609,"passed_time":0.3206823019,"remaining_time":0.2050263897},
{"learn":[3.710755648],"iteration":610,"passed_time":0.3211794586,"remaining_time":0.2044825031},
{"learn":[3.708668039],"iteration":611,"passed_time":0.3216820736,"remaining_time":0.2039422296},
{"learn":[3.705623591],"iteration":612,"passed_time":0.3221719804,"remaining_time":0.2033940562},
{"learn":[3.704045802],"iteration":613,"passed_time":0.3225556394,"remaining_time":0.2027792782},
{"learn":[3.699915209],"iteration":614,"passed_time":0.3229587564,"remaining_time":0.2021774329},
{"learn":[3.696182221],"iteration":615,"passed_time":0.3233824563,"remaining_time":0.2015890636},
{"learn":[3.694263278],"iteration":616,"passed_time":0.323777365,"remaining_time":0.2009833563},
{"learn":[3.693810229],"iteration":617,"passed_time":0.3241744404,"remaining_time":0.2003796703},
{"learn":[3.690900932],"iteration":618,"passed_time":0.3246281814,"remaining_time":0.19981153},
{"learn":[3.688020895],"iteration":619,"passed_time":0.3250460897,"remaining_time":0.1992217969},
{"learn":[3.685491894],"iteration":620,"passed_time":0.3254283737,"remaining_time":0.1986108754},
{"learn":[3.684328128],"iteration":621,"passed_time":0.3258192409,"remaining_time":0.1980059052},
{"learn":[3.680640153],"iteration":622,"passed_time":0.3262413575,"remaining_time":0.1974205325},
{"learn":[3.678932783],"iteration":623,"passed_time":0.3266484743,"remaining_time":0.1968266448},
{"learn":[3.674167041],"iteration":624,"passed_time":0.3270427165,"remaining_time":0.1962256299},
{"learn":[3.672200976],"iteration":625,"passed_time":0.3274665413,"remaining_time":0.1956429496},
{"learn":[3.670606604],"iteration":626,"passed_time":0.3278844913,"remaining_time":0.1950572811},
{"learn":[3.665506042],"iteration":627,"passed_time":0.3282778168,"remaining_time":0.1944575603},
{"learn":[3.664214007],"iteration":628,"passed_time":0.3286831837,"remaining_time":0.193865598},
{"learn":[3.66261643],"iteration":629,"passed_time":0.3291488411,"remaining_time":0.1933096368},
{"learn":[3.662118449],"iteration":630,"passed_time":0.3296212483,"remaining_time":0.1927579091},
{"learn":[3.660871366],"iteration":631,"passed_time":0.330020157,"remaining_time":0.1921636357},
{"learn":[3.656695243],"iteration":632,"passed_time":0.3304116492,"remaining_time":0.1915656797},
{"learn":[3.654497801],"iteration":633,"passed_time":0.330804183,"remaining_time":0.1909689763},
{"learn":[3.654189134],"iteration":634,"passed_time":0.3312347994,"remaining_time":0.1903948059},
{"learn":[3.653957699],"iteration":635,"passed_time":0.3316145001,"remaining_time":0.1897919466},
{"learn":[3.651920725],"iteration":636,"passed_time":0.3321916136,"remaining_time":0.1893022853},
{"learn":[3.65106705],"iteration":637,"passed_time":0.3326553127,"remaining_time":0.1887479987},
{"learn":[3.650612844],"iteration":638,"passed_time":0.3330959289,"remaining_time":0.1881809551},
{"learn":[3.649884732],"iteration":639,"passed_time":0.3335687528,"remaining_time":0.1876324234},
{"learn":[3.646276182],"iteration":640,"passed_time":0.3339974109,"remaining_time":0.1870593924},
{"learn":[3.645808194],"iteration":641,"passed_time":0.3343834031,"remaining_time":0.1864630192},
{"learn":[3.645042989],"iteration":642,"passed_time":0.3348086863,"remaining_time":0.1858891151},
{"learn":[3.639864499],"iteration":643,"passed_time":0.3352167198,"remaining_time":0.1853061371},
{"learn":[3.637318478],"iteration":644,"passed_time":0.3356570444,"remaining_time":0.184741474},
{"learn":[3.636344905],"iteration":645,"passed_time":0.3361068271,"remaining_time":0.1841823789},
{"learn":[3.634754643],"iteration":646,"passed_time":0.3364885278,"remaining_time":0.1835864765},
{"learn":[3.630724975],"iteration":647,"passed_time":0.3368717701,"remaining_time":0.1829920726},
{"learn":[3.629408252],"iteration":648,"passed_time":0.3372823452,"remaining_time":0.182413102},
{"learn":[3.62790646],"iteration":649,"passed_time":0.3377057951,"remaining_time":0.181841582},
{"learn":[3.627388973],"iteration":650,"passed_time":0.3383656153,"remaining_time":0.1813972346},
{"learn":[3.625163557],"iteration":651,"passed_time":0.3388456057,"remaining_time":0.1808562435},
{"learn":[3.623701985],"iteration":652,"passed_time":0.3392291813,"remaining_time":0.1802642051},
{"learn":[3.622342639],"iteration":653,"passed_time":0.3396243401,"remaining_time":0.1796789322},
{"learn":[3.621130639],"iteration":654,"passed_time":0.3400132907,"remaining_time":0.1790909699},
{"learn":[3.619125665],"iteration":655,"passed_time":0.3404468653,"remaining_time":0.1785270148},
{"learn":[3.618878783],"iteration":656,"passed_time":0.3408432324,"remaining_time":0.1779440315},
{"learn":[3.616207429],"iteration":657,"passed_time":0.3412289747,"remaining_time":0.1773560932},
{"learn":[3.61206486],"iteration":658,"passed_time":0.3416154253,"remaining_time":0.1767691351},
{"learn":[3.611955873],"iteration":659,"passed_time":0.3420097091,"remaining_time":0.1761868199},
{"learn":[3.610713743],"iteration":660,"passed_time":0.3424406588,"remaining_time":0.175623878},
{"learn":[3.610044025],"iteration":661,"passed_time":0.3428049849,"remaining_time":0.1750273186},
{"learn":[3.607342669],"iteration":662,"passed_time":0.3431662277,"remaining_time":0.1744298925},
{"learn":[3.602510618],"iteration":663,"passed_time":0.3435570949,"remaining_time":0.1738481685},
{"learn":[3.600492392],"iteration":664,"passed_time":0.3439300874,"remaining_time":0.173258014},
{"learn":[3.597171065],"iteration":665,"passed_time":0.3443217463,"remaining_time":0.1726778728},
{"learn":[3.594358798],"iteration":666,"passed_time":0.3446913222,"remaining_time":0.1720872718},
{"learn":[3.593945251],"iteration":667,"passed_time":0.3451335634,"remaining_time":0.1715334477},
{"learn":[3.593607748],"iteration":668,"passed_time":0.3455378053,"remaining_time":0.1709611563},
{"learn":[3.592238714],"iteration":669,"passed_time":0.3459315891,"remaining_time":0.1703842155},
{"learn":[3.590144654],"iteration":670,"passed_time":0.3463296645,"remaining_time":0.1698099249},
{"learn":[3.587151536],"iteration":671,"passed_time":0.346706782,"remaining_time":0.1692259293},
{"learn":[3.586070865],"iteration":672,"passed_time":0.3471499398,"remaining_time":0.1686746364},
{"learn":[3.585102746],"iteration":673,"passed_time":0.3475958892,"remaining_time":0.1681250147},
{"learn":[3.584362847],"iteration":674,"passed_time":0.3479788815,"remaining_time":0.1675453874},
{"learn":[3.581407561],"iteration":675,"passed_time":0.3483645822,"remaining_time":0.16696764},
{"learn":[3.57919422],"iteration":676,"passed_time":0.3488706554,"remaining_time":0.1664478902},
{"learn":[3.577632204],"iteration":677,"passed_time":0.3493305629,"remaining_time":0.1659062555},
{"learn":[3.573911195],"iteration":678,"passed_time":0.3497860538,"remaining_time":0.1653627736},
{"learn":[3.573408216],"iteration":679,"passed_time":0.3502154202,"remaining_time":0.1648072566},
{"learn":[3.571076482],"iteration":680,"passed_time":0.3506396617,"remaining_time":0.1642497094},
{"learn":[3.568177107],"iteration":681,"passed_time":0.3510469452,"remaining_time":0.163684646},
{"learn":[3.564824621],"iteration":682,"passed_time":0.3514385624,"remaining_time":0.1631127735},
{"learn":[3.562475026],"iteration":683,"passed_time":0.3518617206,"remaining_time":0.1625559996},
{"learn":[3.561226889],"iteration":684,"passed_time":0.3522350882,"remaining_time":0.1619767194},
{"learn":[3.559383467],"iteration":685,"passed_time":0.3527043705,"remaining_time":0.1614419422},
{"learn":[3.555209766],"iteration":686,"passed_time":0.3531889441,"remaining_time":0.1609143224},
{"learn":[3.55345383],"iteration":687,"passed_time":0.3536207272,"remaining_time":0.1603628879},
{"learn":[3.552300968],"iteration":688,"passed_time":0.3541747161,"remaining_time":0.1598669618},
{"learn":[3.551253986],"iteration":689,"passed_time":0.3545454587,"remaining_time":0.1592885394},
{"learn":[3.549807725],"iteration":690,"passed_time":0.3550384905,"remaining_time":0.1587654031},
{"learn":[3.547992926],"iteration":691,"passed_time":0.3554390242,"remaining_time":0.1582011842},
{"learn":[3.545438607],"iteration":692,"passed_time":0.3558115584,"remaining_time":0.1576250338},
{"learn":[3.543313763],"iteration":693,"passed_time":0.3562298,"remaining_time":0.1570696236},
{"learn":[3.542962896],"iteration":694,"passed_time":0.3566224589,"remaining_time":0.1565033812},
{"learn":[3.539800465],"iteration":695,"passed_time":0.3570556169,"remaining_time":0.1559553269},
{"learn":[3.53953187],"iteration":696,"passed_time":0.3575093995,"remaining_time":0.1554165682},
{"learn":[3.536332425],"iteration":697,"passed_time":0.3579435575,"remaining_time":0.1548695621},
{"learn":[3.534993327],"iteration":698,"passed_time":0.3583400912,"remaining_time":0.1543066773},
{"learn":[3.531637011],"iteration":699,"passed_time":0.3587774575,"remaining_time":0.1537617675},
{"learn":[3.531040284],"iteration":700,"passed_time":0.359283489,"remaining_time":0.1532464525},
{"learn":[3.529973872],"iteration":701,"passed_time":0.3597243969,"remaining_time":0.1527035189},
{"learn":[3.527325183],"iteration":702,"passed_time":0.3601417636,"remaining_time":0.15215093},
{"learn":[3.527200815],"iteration":703,"passed_time":0.3605730883,"remaining_time":0.1516045939},
{"learn":[3.523459911],"iteration":704,"passed_time":0.3611742013,"remaining_time":0.1511296303},
{"learn":[3.522729934],"iteration":705,"passed_time":0.3616074843,"remaining_time":0.1505844198},
{"learn":[3.522260582],"iteration":706,"passed_time":0.3620419756,"remaining_time":0.1500400267},
{"learn":[3.518641591],"iteration":707,"passed_time":0.3624488425,"remaining_time":0.1494845508},
{"learn":[3.516856405],"iteration":708,"passed_time":0.3629459159,"remaining_time":0.1489665184},
{"learn":[3.515083413],"iteration":709,"passed_time":0.3633465329,"remaining_time":0.1484091472},
{"learn":[3.514671214],"iteration":710,"passed_time":0.3638153568,"remaining_time":0.1478799411},
{"learn":[3.512617621],"iteration":711,"passed_time":0.3642139322,"remaining_time":0.1473224894},
{"learn":[3.510747971],"iteration":712,"passed_time":0.3646157575,"remaining_time":0.1467667916},
{"learn":[3.508149266],"iteration":713,"passed_time":0.3650409157,"remaining_time":0.146220871},
{"learn":[3.504557165],"iteration":714,"passed_time":0.3654094083,"remaining_time":0.1456527012},
{"learn":[3.501367208],"iteration":715,"passed_time":0.3658996485,"remaining_time":0.1451333801},
{"learn":[3.497593362],"iteration":716,"passed_time":0.3662763077,"remaining_time":0.1445693097},
{"learn":[3.496291169],"iteration":717,"passed_time":0.3666373421,"remaining_time":0.1439996246},
{"learn":[3.49330374],"iteration":718,"passed_time":0.3669967933,"remaining_time":0.1434299011},
{"learn":[3.490044385],"iteration":719,"passed_time":0.367362661,"remaining_time":0.142863257},
{"learn":[3.488891789],"iteration":720,"passed_time":0.3677916941,"remaining_time":0.1423216125},
{"learn":[3.486869081],"iteration":721,"passed_time":0.3683078088,"remaining_time":0.14181381},
{"learn":[3.486303638],"iteration":722,"passed_time":0.3687332169,"remaining_time":0.1412712325},
{"learn":[3.486035862],"iteration":723,"passed_time":0.3691859162,"remaining_time":0.1407393824},
{"learn":[3.482668951],"iteration":724,"passed_time":0.369631324,"remaining_time":0.140204985},
{"learn":[3.47820549],"iteration":725,"passed_time":0.3700246495,"remaining_time":0.1396511762},
{"learn":[3.474392283],"iteration":726,"passed_time":0.3704248498,"remaining_time":0.1391003906},
{"learn":[3.472268163],"iteration":727,"passed_time":0.3708330083,"remaining_time":0.1385529921},
{"learn":[3.471209164],"iteration":728,"passed_time":0.371313207,"remaining_time":0.138032756},
{"learn":[3.470049971],"iteration":729,"passed_time":0.3718417382,"remaining_time":0.1375305059},
{"learn":[3.469078654],"iteration":730,"passed_time":0.3722368136,"remaining_time":0.1369790737},
{"learn":[3.468643292],"iteration":731,"passed_time":0.3726403889,"remaining_time":0.1364311806},
{"learn":[3.468134848],"iteration":732,"passed_time":0.3730307977,"remaining_time":0.1358788854},
{"learn":[3.467820182],"iteration":733,"passed_time":0.3734217066,"remaining_time":0.1353272125},
{"learn":[3.465776156],"iteration":734,"passed_time":0.3738259902,"remaining_time":0.1347807992},
{"learn":[3.463037608],"iteration":735,"passed_time":0.3742647314,"remaining_time":0.1342471319},
{"learn":[3.45965637],"iteration":736,"passed_time":0.3746393906,"remaining_time":0.1336908544},
{"learn":[3.457275091],"iteration":737,"passed_time":0.3750343827,"remaining_time":0.1331422876},
{"learn":[3.455522955],"iteration":738,"passed_time":0.3754408746,"remaining_time":0.1325981979},
{"learn":[3.451270508],"iteration":739,"passed_time":0.3758318668,"remaining_time":0.1320490343},
{"learn":[3.450978947],"iteration":740,"passed_time":0.3762234006,"remaining_time":0.1315004869},
{"learn":[3.450608492],"iteration":741,"passed_time":0.3766251426,"remaining_time":0.1309559121},
{"learn":[3.448122004],"iteration":742,"passed_time":0.3770696337,"remaining_time":0.1304265086},
{"learn":[3.445646714],"iteration":743,"passed_time":0.3774769589,"remaining_time":0.129884545},
{"learn":[3.44411263],"iteration":744,"passed_time":0.3778638262,"remaining_time":0.1293359405},
{"learn":[3.443264164],"iteration":745,"passed_time":0.3782507351,"remaining_time":0.1287877838},
{"learn":[3.439521363],"iteration":746,"passed_time":0.3786379774,"remaining_time":0.1282401717},
{"learn":[3.436809225],"iteration":747,"passed_time":0.3790544691,"remaining_time":0.1277028425},
{"learn":[3.435509465],"iteration":748,"passed_time":0.3794722524,"remaining_time":0.1271662688},
{"learn":[3.434450277],"iteration":749,"passed_time":0.3798653695,"remaining_time":0.1266217898},
{"learn":[3.431786753],"iteration":750,"passed_time":0.3802608616,"remaining_time":0.1260785014},
{"learn":[3.430150302],"iteration":751,"passed_time":0.3806658119,"remaining_time":0.1255387252},
{"learn":[3.42696281],"iteration":752,"passed_time":0.3810878868,"remaining_time":0.1250049243},
{"learn":[3.426870334],"iteration":753,"passed_time":0.3814891288,"remaining_time":0.1244646229},
{"learn":[3.425200309],"iteration":754,"passed_time":0.381911537,"remaining_time":0.1239315584},
{"learn":[3.423383783],"iteration":755,"passed_time":0.382309029,"remaining_time":0.1233907448},
{"learn":[3.422752979],"iteration":756,"passed_time":0.3827023129,"remaining_time":0.1228489591},
{"learn":[3.420845924],"iteration":757,"passed_time":0.3831031382,"remaining_time":0.1223099729},
{"learn":[3.418917862],"iteration":758,"passed_time":0.3835197549,"remaining_time":0.1217763648},
{"learn":[3.417095735],"iteration":759,"passed_time":0.3839872038,"remaining_time":0.121259117},
{"learn":[3.414391848],"iteration":760,"passed_time":0.3843927374,"remaining_time":0.1207225549},
{"learn":[3.41426711],"iteration":761,"passed_time":0.3848586864,"remaining_time":0.1202052065},
{"learn":[3.411976013],"iteration":762,"passed_time":0.3853331353,"remaining_time":0.1196906331},
{"learn":[3.408614844],"iteration":763,"passed_time":0.3857168776,"remaining_time":0.1191481454},
{"learn":[3.407906721],"iteration":764,"passed_time":0.3861109948,"remaining_time":0.1186092598},
{"learn":[3.407494015],"iteration":765,"passed_time":0.3865642357,"remaining_time":0.1180888135},
{"learn":[3.406287128],"iteration":766,"passed_time":0.3869748942,"remaining_time":0.1175556067},
{"learn":[3.404600442],"iteration":767,"passed_time":0.3873685113,"remaining_time":0.1170175711},
{"learn":[3.404012662],"iteration":768,"passed_time":0.3877930028,"remaining_time":0.1164891855},
{"learn":[3.400398762],"iteration":769,"passed_time":0.388316284,"remaining_time":0.1159905783},
{"learn":[3.399737714],"iteration":770,"passed_time":0.3887279841,"remaining_time":0.1154587657},
{"learn":[3.399185251],"iteration":771,"passed_time":0.3891193513,"remaining_time":0.1149212592},
{"learn":[3.397245411],"iteration":772,"passed_time":0.3895245099,"remaining_time":0.1143881808},
{"learn":[3.396229831],"iteration":773,"passed_time":0.3899207103,"remaining_time":0.1138528172},
{"learn":[3.394002836],"iteration":774,"passed_time":0.3903356187,"remaining_time":0.1133232441},
{"learn":[3.389617243],"iteration":775,"passed_time":0.390752527,"remaining_time":0.1127945439},
{"learn":[3.385426488],"iteration":776,"passed_time":0.391288433,"remaining_time":0.1123002839},
{"learn":[3.385072258],"iteration":777,"passed_time":0.3916832168,"remaining_time":0.111765648},
{"learn":[3.383842366],"iteration":778,"passed_time":0.392087417,"remaining_time":0.1112340426},
{"learn":[3.380110746],"iteration":779,"passed_time":0.3924844924,"remaining_time":0.1107007543},
{"learn":[3.378595218],"iteration":780,"passed_time":0.3928556517,"remaining_time":0.1101605477},
{"learn":[3.377371219],"iteration":781,"passed_time":0.3932479772,"remaining_time":0.1096266739},
{"learn":[3.375814782],"iteration":782,"passed_time":0.3936442609,"remaining_time":0.1090942588},
{"learn":[3.374195887],"iteration":783,"passed_time":0.3940384614,"remaining_time":0.1085616169},
{"learn":[3.373704309],"iteration":784,"passed_time":0.3944419117,"remaining_time":0.1080318612},
{"learn":[3.372971757],"iteration":785,"passed_time":0.394808696,"remaining_time":0.1074924439},
{"learn":[3.371565136],"iteration":786,"passed_time":0.3951915633,"remaining_time":0.1069578183},
{"learn":[3.3700309],"iteration":787,"passed_time":0.3955895554,"remaining_time":0.1064276469},
{"learn":[3.368186663],"iteration":788,"passed_time":0.3959924223,"remaining_time":0.1058991142},
{"learn":[3.366710398],"iteration":789,"passed_time":0.3963889561,"remaining_time":0.1053692162},
{"learn":[3.364598042],"iteration":790,"passed_time":0.3967636153,"remaining_time":0.1048338756},
{"learn":[3.36348442],"iteration":791,"passed_time":0.3971308579,"remaining_time":0.104296993},
{"learn":[3.362001759],"iteration":792,"passed_time":0.3975315166,"remaining_time":0.103769261},
{"learn":[3.361580401],"iteration":793,"passed_time":0.397927217,"remaining_time":0.1032405626},
{"learn":[3.359543675],"iteration":794,"passed_time":0.3983215841,"remaining_time":0.102711855},
{"learn":[3.35766119],"iteration":795,"passed_time":0.3987130763,"remaining_time":0.1021827482},
{"learn":[3.354592969],"iteration":796,"passed_time":0.3991310263,"remaining_time":0.1016607256},
{"learn":[3.350985986],"iteration":797,"passed_time":0.3995510596,"remaining_time":0.1011394913},
{"learn":[3.349589624],"iteration":798,"passed_time":0.4000390498,"remaining_time":0.1006356058},
{"learn":[3.349110856],"iteration":799,"passed_time":0.4004970824,"remaining_time":0.1001242706},
{"learn":[3.345315441],"iteration":800,"passed_time":0.4009097824,"remaining_time":0.09960180612},
{"learn":[3.34397474],"iteration":801,"passed_time":0.4013160243,"remaining_time":0.09907802097},
{"learn":[3.343800902],"iteration":802,"passed_time":0.4017237245,"remaining_time":0.09855488634},
{"learn":[3.342329465],"iteration":803,"passed_time":0.4022421308,"remaining_time":0.09805902692},
{"learn":[3.34220347],"iteration":804,"passed_time":0.4026884969,"remaining_time":0.09754566074},
{"learn":[3.341279219],"iteration":805,"passed_time":0.403100572,"remaining_time":0.09702420716},
{"learn":[3.337329521],"iteration":806,"passed_time":0.4035842707,"remaining_time":0.09652015395},
{"learn":[3.336708453],"iteration":807,"passed_time":0.4040458448,"remaining_time":0.09601089381},
{"learn":[3.333252703],"iteration":808,"passed_time":0.4044518783,"remaining_time":0.09548863877},
{"learn":[3.332186769],"iteration":809,"passed_time":0.4048936612,"remaining_time":0.09497505633},
{"learn":[3.330594851],"iteration":810,"passed_time":0.4052660287,"remaining_time":0.09444547402},
{"learn":[3.327867442],"iteration":811,"passed_time":0.4056846871,"remaining_time":0.09392699651},
{"learn":[3.327563111],"iteration":812,"passed_time":0.4060959288,"remaining_time":0.09340705866},
{"learn":[3.326308994],"iteration":813,"passed_time":0.4065203787,"remaining_time":0.09289040594},
{"learn":[3.326249879],"iteration":814,"passed_time":0.4069226623,"remaining_time":0.09236894789},
{"learn":[3.322336238],"iteration":815,"passed_time":0.4074390687,"remaining_time":0.09187351548},
{"learn":[3.320491154],"iteration":816,"passed_time":0.4079323505,"remaining_time":0.09137285207},
{"learn":[3.320434271],"iteration":817,"passed_time":0.4083433839,"remaining_time":0.09085390694},
{"learn":[3.319609638],"iteration":818,"passed_time":0.4087529591,"remaining_time":0.09033490305},
{"learn":[3.316182682],"iteration":819,"passed_time":0.4091529928,"remaining_time":0.08981407158},
{"learn":[3.313126612],"iteration":820,"passed_time":0.4095358601,"remaining_time":0.08928979167},
{"learn":[3.311222803],"iteration":821,"passed_time":0.4099401854,"remaining_time":0.08877050243},
{"learn":[3.309627335],"iteration":822,"passed_time":0.4104055511,"remaining_time":0.08826462034},
{"learn":[3.307974895],"iteration":823,"passed_time":0.4107810019,"remaining_time":0.08773963147},
{"learn":[3.307321505],"iteration":824,"passed_time":0.411241076,"remaining_time":0.08723295553},
{"learn":[3.306759087],"iteration":825,"passed_time":0.4116410264,"remaining_time":0.08671372711},
{"learn":[3.30484037],"iteration":826,"passed_time":0.41204181,"remaining_time":0.08619496147},
{"learn":[3.30201994],"iteration":827,"passed_time":0.4125276753,"remaining_time":0.08569415478},
{"learn":[3.299302297],"iteration":828,"passed_time":0.4129170009,"remaining_time":0.08517347063},
{"learn":[3.298132671],"iteration":829,"passed_time":0.4133330343,"remaining_time":0.08465857328},
{"learn":[3.296976183],"iteration":830,"passed_time":0.4137501093,"remaining_time":0.08414412571},
{"learn":[3.293144745],"iteration":831,"passed_time":0.4141483513,"remaining_time":0.0836261094},
{"learn":[3.290284404],"iteration":832,"passed_time":0.4146551328,"remaining_time":0.08313014068},
{"learn":[3.288285745],"iteration":833,"passed_time":0.4150790827,"remaining_time":0.08261765915},
{"learn":[3.286662667],"iteration":834,"passed_time":0.4154913245,"remaining_time":0.08210307609},
{"learn":[3.285692682],"iteration":835,"passed_time":0.4158911082,"remaining_time":0.08158629394},
{"learn":[3.284565611],"iteration":836,"passed_time":0.4162628091,"remaining_time":0.08106432243},
{"learn":[3.283897383],"iteration":837,"passed_time":0.4167039252,"remaining_time":0.08055612875},
{"learn":[3.280712855],"iteration":838,"passed_time":0.4171054172,"remaining_time":0.08004049127},
{"learn":[3.280468341],"iteration":839,"passed_time":0.4174797847,"remaining_time":0.079519959},
{"learn":[3.277814895],"iteration":840,"passed_time":0.4178700269,"remaining_time":0.07900277561},
{"learn":[3.276316385],"iteration":841,"passed_time":0.4182632274,"remaining_time":0.07848644885},
{"learn":[3.27557063],"iteration":842,"passed_time":0.418649678,"remaining_time":0.07796915712},
{"learn":[3.27499628],"iteration":843,"passed_time":0.4190347953,"remaining_time":0.077451929},
{"learn":[3.273569958],"iteration":844,"passed_time":0.4195116192,"remaining_time":0.07695183547},
{"learn":[3.269665595],"iteration":845,"passed_time":0.4199071946,"remaining_time":0.07643700705},
{"learn":[3.267984685],"iteration":846,"passed_time":0.4203288112,"remaining_time":0.07592716424},
{"learn":[3.267702508],"iteration":847,"passed_time":0.4207436779,"remaining_time":0.07541631962},
{"learn":[3.266671924],"iteration":848,"passed_time":0.4211522947,"remaining_time":0.07490458952},
{"learn":[3.265359825],"iteration":849,"passed_time":0.4215460368,"remaining_time":0.07439047709},
{"learn":[3.2618983],"iteration":850,"passed_time":0.421952987,"remaining_time":0.07387896013},
{"learn":[3.260456253],"iteration":851,"passed_time":0.4224114779,"remaining_time":0.0733766417},
{"learn":[3.258389147],"iteration":852,"passed_time":0.4228093866,"remaining_time":0.07286398573},
{"learn":[3.258108469],"iteration":853,"passed_time":0.4232770856,"remaining_time":0.07236352986},
{"learn":[3.256424936],"iteration":854,"passed_time":0.423659703,"remaining_time":0.07184872155},
{"learn":[3.254817983],"iteration":855,"passed_time":0.4240512785,"remaining_time":0.07133572909},
{"learn":[3.253898449],"iteration":856,"passed_time":0.4245238524,"remaining_time":0.07083653546},
{"learn":[3.253023652],"iteration":857,"passed_time":0.4249781349,"remaining_time":0.07033437665},
{"learn":[3.252845542],"iteration":858,"passed_time":0.4253649606,"remaining_time":0.06982125662},
{"learn":[3.252316026],"iteration":859,"passed_time":0.4257384114,"remaining_time":0.06930625302},
{"learn":[3.24975301],"iteration":860,"passed_time":0.4261865275,"remaining_time":0.06880363219},
{"learn":[3.249151075],"iteration":861,"passed_time":0.4265661449,"remaining_time":0.06829017169},
{"learn":[3.246257135],"iteration":862,"passed_time":0.4270263857,"remaining_time":0.06778982021},
{"learn":[3.243826471],"iteration":863,"passed_time":0.427428086,"remaining_time":0.06728034687},
{"learn":[3.243190653],"iteration":864,"passed_time":0.4278372028,"remaining_time":0.06677228021},
{"learn":[3.24008797],"iteration":865,"passed_time":0.4282411114,"remaining_time":0.06626363618},
{"learn":[3.240036811],"iteration":866,"passed_time":0.4287211018,"remaining_time":0.0657669049},
{"learn":[3.238676314],"iteration":867,"passed_time":0.4291911341,"remaining_time":0.06526869781},
{"learn":[3.237848782],"iteration":868,"passed_time":0.4297407481,"remaining_time":0.06478255237},
{"learn":[3.236405498],"iteration":869,"passed_time":0.430181531,"remaining_time":0.06427999888},
{"learn":[3.233378068],"iteration":870,"passed_time":0.4306512716,"remaining_time":0.06378187605},
{"learn":[3.233169169],"iteration":871,"passed_time":0.4310814713,"remaining_time":0.06327801414},
{"learn":[3.232434885],"iteration":872,"passed_time":0.4314703386,"remaining_time":0.06276830813},
{"learn":[3.229978115],"iteration":873,"passed_time":0.4318582892,"remaining_time":0.06225874649},
{"learn":[3.229648848],"iteration":874,"passed_time":0.4322641561,"remaining_time":0.06175202229},
{"learn":[3.227208761],"iteration":875,"passed_time":0.4328570609,"remaining_time":0.06127200405},
{"learn":[3.226258869],"iteration":876,"passed_time":0.4333484261,"remaining_time":0.06077748735},
{"learn":[3.225331995],"iteration":877,"passed_time":0.4337921255,"remaining_time":0.06027635457},
{"learn":[3.221968268],"iteration":878,"passed_time":0.4342173254,"remaining_time":0.05977280588},
{"learn":[3.221166317],"iteration":879,"passed_time":0.434618234,"remaining_time":0.05926612282},
{"learn":[3.220047503],"iteration":880,"passed_time":0.4350274342,"remaining_time":0.05876079985},
{"learn":[3.21982781],"iteration":881,"passed_time":0.4355747566,"remaining_time":0.05827417378},
{"learn":[3.216693405],"iteration":882,"passed_time":0.436102746,"remaining_time":0.05778484857},
{"learn":[3.214798761],"iteration":883,"passed_time":0.4364963632,"remaining_time":0.05727780331},
{"learn":[3.214395085],"iteration":884,"passed_time":0.4369030217,"remaining_time":0.05677270904},
{"learn":[3.213470696],"iteration":885,"passed_time":0.4373290965,"remaining_time":0.05627033522},
{"learn":[3.211595017],"iteration":886,"passed_time":0.4377884207,"remaining_time":0.05577236927},
{"learn":[3.210965255],"iteration":887,"passed_time":0.4382035791,"remaining_time":0.05526891988},
{"learn":[3.209413583],"iteration":888,"passed_time":0.4386053627,"remaining_time":0.05476399917},
{"learn":[3.208331683],"iteration":889,"passed_time":0.4390341875,"remaining_time":0.05426265238},
{"learn":[3.207110711],"iteration":890,"passed_time":0.4394396794,"remaining_time":0.05375861397},
{"learn":[3.204519413],"iteration":891,"passed_time":0.4399238364,"remaining_time":0.053264321},
{"learn":[3.201421296],"iteration":892,"passed_time":0.4403687858,"remaining_time":0.05276535284},
{"learn":[3.200691259],"iteration":893,"passed_time":0.4408867755,"remaining_time":0.05227516577},
{"learn":[3.200485067],"iteration":894,"passed_time":0.441279476,"remaining_time":0.05177021785},
{"learn":[3.197467568],"iteration":895,"passed_time":0.4417015925,"remaining_time":0.05126893485},
{"learn":[3.195838544],"iteration":896,"passed_time":0.442175833,"remaining_time":0.0507738136},
{"learn":[3.195671746],"iteration":897,"passed_time":0.4425775334,"remaining_time":0.05027049933},
{"learn":[3.194213094],"iteration":898,"passed_time":0.442997275,"remaining_time":0.04976943801},
{"learn":[3.192884691],"iteration":899,"passed_time":0.4434387245,"remaining_time":0.04927096939},
{"learn":[3.188364239],"iteration":900,"passed_time":0.4438563411,"remaining_time":0.04877000863},
{"learn":[3.185219478],"iteration":901,"passed_time":0.4442913324,"remaining_time":0.04827112038},
{"learn":[3.184120387],"iteration":902,"passed_time":0.4446883245,"remaining_time":0.04776829178},
{"learn":[3.183725321],"iteration":903,"passed_time":0.4451834396,"remaining_time":0.04727611748},
{"learn":[3.181264554],"iteration":904,"passed_time":0.445647972,"remaining_time":0.04678072634},
{"learn":[3.180741589],"iteration":905,"passed_time":0.4460683386,"remaining_time":0.046280821},
{"learn":[3.179782639],"iteration":906,"passed_time":0.4464871219,"remaining_time":0.04578092871},
{"learn":[3.176377564],"iteration":907,"passed_time":0.4469154884,"remaining_time":0.04528218604},
{"learn":[3.174078182],"iteration":908,"passed_time":0.4473624378,"remaining_time":0.04478545857},
{"learn":[3.171242379],"iteration":909,"passed_time":0.447816887,"remaining_time":0.04428958223},
{"learn":[3.170421012],"iteration":910,"passed_time":0.4483565429,"remaining_time":0.0438021211},
{"learn":[3.170087224],"iteration":911,"passed_time":0.4487733679,"remaining_time":0.04330269339},
{"learn":[3.167303059],"iteration":912,"passed_time":0.4492154841,"remaining_time":0.04280585664},
{"learn":[3.16705966],"iteration":913,"passed_time":0.4495920182,"remaining_time":0.04230296889},
{"learn":[3.165667683],"iteration":914,"passed_time":0.4501617152,"remaining_time":0.04181830141},
{"learn":[3.164689733],"iteration":915,"passed_time":0.4506084979,"remaining_time":0.04132217666},
{"learn":[3.163311455],"iteration":916,"passed_time":0.4510459475,"remaining_time":0.04082531477},
{"learn":[3.159425016],"iteration":917,"passed_time":0.4514844387,"remaining_time":0.04032867536},
{"learn":[3.159327058],"iteration":918,"passed_time":0.4519120969,"remaining_time":0.03983120767},
{"learn":[3.15819426],"iteration":919,"passed_time":0.4523997538,"remaining_time":0.03933910903},
{"learn":[3.157086603],"iteration":920,"passed_time":0.4527989958,"remaining_time":0.03883943612},
{"learn":[3.153354154],"iteration":921,"passed_time":0.4532033211,"remaining_time":0.03834041111},
{"learn":[3.153261317],"iteration":922,"passed_time":0.4536346875,"remaining_time":0.03784384717},
{"learn":[3.153168454],"iteration":923,"passed_time":0.4540453043,"remaining_time":0.03734571767},
{"learn":[3.152080399],"iteration":924,"passed_time":0.4545018368,"remaining_time":0.03685150028},
{"learn":[3.151635144],"iteration":925,"passed_time":0.4549209534,"remaining_time":0.03635437425},
{"learn":[3.147762655],"iteration":926,"passed_time":0.4554120269,"remaining_time":0.03586308303},
{"learn":[3.147172317],"iteration":927,"passed_time":0.4558353102,"remaining_time":0.03536653268},
{"learn":[3.146254125],"iteration":928,"passed_time":0.45625926,"remaining_time":0.03487019102},
{"learn":[3.144869828],"iteration":929,"passed_time":0.4566945847,"remaining_time":0.03437486121},
{"learn":[3.143466218],"iteration":930,"passed_time":0.4570908267,"remaining_time":0.03387676374},
{"learn":[3.141919643],"iteration":931,"passed_time":0.4574941104,"remaining_time":0.03337939861},
{"learn":[3.141054135],"iteration":932,"passed_time":0.4579561011,"remaining_time":0.03288645099},
{"learn":[3.139390417],"iteration":933,"passed_time":0.4583993423,"remaining_time":0.03239224474},
{"learn":[3.139025283],"iteration":934,"passed_time":0.4587922094,"remaining_time":0.03189464557},
{"learn":[3.137824183],"iteration":935,"passed_time":0.4592597417,"remaining_time":0.0314023755},
{"learn":[3.135620453],"iteration":936,"passed_time":0.4597008996,"remaining_time":0.03090838493},
{"learn":[3.13443178],"iteration":937,"passed_time":0.4600921835,"remaining_time":0.03041121042},
{"learn":[3.132765713],"iteration":938,"passed_time":0.4605245498,"remaining_time":0.02991693029},
{"learn":[3.131434124],"iteration":939,"passed_time":0.4609216669,"remaining_time":0.02942053193},
{"learn":[3.128384262],"iteration":940,"passed_time":0.4614511563,"remaining_time":0.02893264423},
{"learn":[3.128120455],"iteration":941,"passed_time":0.4618810227,"remaining_time":0.02843853431},
{"learn":[3.126314615],"iteration":942,"passed_time":0.4623452218,"remaining_time":0.02794663589},
{"learn":[3.125409666],"iteration":943,"passed_time":0.4627450055,"remaining_time":0.0274509749},
{"learn":[3.123072589],"iteration":944,"passed_time":0.4631877049,"remaining_time":0.02695801457},
{"learn":[3.122921099],"iteration":945,"passed_time":0.4636854867,"remaining_time":0.02646830474},
{"learn":[3.122182662],"iteration":946,"passed_time":0.4640892286,"remaining_time":0.0259733148},
{"learn":[3.120040951],"iteration":947,"passed_time":0.4645365947,"remaining_time":0.02548091026},
{"learn":[3.118767799],"iteration":948,"passed_time":0.465005627,"remaining_time":0.02498976499},
{"learn":[3.118203218],"iteration":949,"passed_time":0.4654859507,"remaining_time":0.02449926056},
{"learn":[3.116343362],"iteration":950,"passed_time":0.4659397333,"remaining_time":0.02400741002},
{"learn":[3.11480829],"iteration":951,"passed_time":0.4663327671,"remaining_time":0.02351257649},
{"learn":[3.112607903],"iteration":952,"passed_time":0.4667614669,"remaining_time":0.02301971558},
{"learn":[3.111661241],"iteration":953,"passed_time":0.4671855001,"remaining_time":0.02252676415},
{"learn":[3.110249676],"iteration":954,"passed_time":0.4675848671,"remaining_time":0.02203279478},
{"learn":[3.107333579],"iteration":955,"passed_time":0.4680229,"remaining_time":0.02154080293},
{"learn":[3.107149851],"iteration":956,"passed_time":0.4684277669,"remaining_time":0.02104743362},
{"learn":[3.106867336],"iteration":957,"passed_time":0.4688324672,"remaining_time":0.02055424178},
{"learn":[3.10364681],"iteration":958,"passed_time":0.4692582087,"remaining_time":0.02006213405},
{"learn":[3.102703811],"iteration":959,"passed_time":0.4696618673,"remaining_time":0.01956924447},
{"learn":[3.101469264],"iteration":960,"passed_time":0.4700540261,"remaining_time":0.0190760739},
{"learn":[3.09863569],"iteration":961,"passed_time":0.4704661012,"remaining_time":0.01858390005},
{"learn":[3.09645939],"iteration":962,"passed_time":0.4708442603,"remaining_time":0.01809058944},
{"learn":[3.096240186],"iteration":963,"passed_time":0.4713511252,"remaining_time":0.01760232418},
{"learn":[3.094838828],"iteration":964,"passed_time":0.4717963246,"remaining_time":0.01711178379},
{"learn":[3.094176802],"iteration":965,"passed_time":0.4722843565,"remaining_time":0.01662284485},
{"learn":[3.093182279],"iteration":966,"passed_time":0.472710973,"remaining_time":0.0161318119},
{"learn":[3.090150687],"iteration":967,"passed_time":0.4731683389,"remaining_time":0.01564192856},
{"learn":[3.088612829],"iteration":968,"passed_time":0.4736017469,"remaining_time":0.01515134588},
{"learn":[3.087153684],"iteration":969,"passed_time":0.4740686959,"remaining_time":0.01466191843},
{"learn":[3.085866843],"iteration":970,"passed_time":0.4745281034,"remaining_time":0.01417231205},
{"learn":[3.082669094],"iteration":971,"passed_time":0.4749662196,"remaining_time":0.01368215448},
{"learn":[3.081047548],"iteration":972,"passed_time":0.4754535016,"remaining_time":0.01319346818},
{"learn":[3.079684322],"iteration":973,"passed_time":0.4758721182,"remaining_time":0.01270295182},
{"learn":[3.07613431],"iteration":974,"passed_time":0.4763211926,"remaining_time":0.01221336391},
{"learn":[3.074005935],"iteration":975,"passed_time":0.4768112244,"remaining_time":0.01172486617},
{"learn":[3.072988853],"iteration":976,"passed_time":0.4772164663,"remaining_time":0.01123436922},
{"learn":[3.072344268],"iteration":977,"passed_time":0.4776456244,"remaining_time":0.0107445846},
{"learn":[3.070654438],"iteration":978,"passed_time":0.4780969488,"remaining_time":0.01025539931},
{"learn":[3.069724506],"iteration":979,"passed_time":0.4785114821,"remaining_time":0.009765540452},
{"learn":[3.067763166],"iteration":980,"passed_time":0.4791534693,"remaining_time":0.009280240486},
{"learn":[3.066737893],"iteration":981,"passed_time":0.4795522114,"remaining_time":0.008790162734},
{"learn":[3.065248174],"iteration":982,"passed_time":0.4800085356,"remaining_time":0.008301266638},
{"learn":[3.063186837],"iteration":983,"passed_time":0.4804133191,"remaining_time":0.007811598685},
{"learn":[3.062880371],"iteration":984,"passed_time":0.4808921429,"remaining_time":0.007323230603},
{"learn":[3.061288645],"iteration":985,"passed_time":0.4812906766,"remaining_time":0.006833741859},
{"learn":[3.059970575],"iteration":986,"passed_time":0.4817083349,"remaining_time":0.006344689315},
{"learn":[3.059576341],"iteration":987,"passed_time":0.4821489928,"remaining_time":0.005856060641},
{"learn":[3.058175919],"iteration":988,"passed_time":0.4825627762,"remaining_time":0.005367230069},
{"learn":[3.056830702],"iteration":989,"passed_time":0.48295681,"remaining_time":0.004878351616},
{"learn":[3.056336579],"iteration":990,"passed_time":0.4833581353,"remaining_time":0.004389730795},
{"learn":[3.055810414],"iteration":991,"passed_time":0.4838041681,"remaining_time":0.003901646517},
{"learn":[3.055476518],"iteration":992,"passed_time":0.4841947019,"remaining_time":0.003413255704},
{"learn":[3.053331734],"iteration":993,"passed_time":0.4845711944,"remaining_time":0.002924977029},
{"learn":[3.050890374],"iteration":994,"passed_time":0.4850060607,"remaining_time":0.002437216386},
{"learn":[3.04972623],"iteration":995,"passed_time":0.4854756763,"remaining_time":0.001949701511},
{"learn":[3.047217327],"iteration":996,"passed_time":0.4860324569,"remaining_time":0.001462484825},
{"learn":[3.047155483],"iteration":997,"passed_time":0.4864678649,"remaining_time":0.0009748855007},
{"learn":[3.04430671],"iteration":998,"passed_time":0.4870257704,"remaining_time":0.0004875132837},
{"learn":[3.042664195],"iteration":999,"passed_time":0.4873981379,"remaining_time":0}
]}